{"nodes": [{"id": "d_development_pixeltales_image_bug_fixed_pixeltales_docu_offline_games_empty_debug_md", "label": "OFFLINE_GAMES_EMPTY_DEBUG.md", "file_type": "document", "source_file": "D:\\Development\\PixelTales(Image bug fixed)\\PixelTales\\docu\\OFFLINE_GAMES_EMPTY_DEBUG.md", "source_location": "L1"}, {"id": "docu_offline_games_empty_debug_offline_games_empty_debug_guide", "label": "Offline Games Empty Debug Guide", "file_type": "document", "source_file": "D:\\Development\\PixelTales(Image bug fixed)\\PixelTales\\docu\\OFFLINE_GAMES_EMPTY_DEBUG.md", "source_location": "L1"}, {"id": "docu_offline_games_empty_debug_issue", "label": "\ud83d\udc1b Issue", "file_type": "document", "source_file": "D:\\Development\\PixelTales(Image bug fixed)\\PixelTales\\docu\\OFFLINE_GAMES_EMPTY_DEBUG.md", "source_location": "L3"}, {"id": "docu_offline_games_empty_debug_debug_steps", "label": "\ud83d\udd0d Debug Steps", "file_type": "document", "source_file": "D:\\Development\\PixelTales(Image bug fixed)\\PixelTales\\docu\\OFFLINE_GAMES_EMPTY_DEBUG.md", "source_location": "L6"}, {"id": "docu_offline_games_empty_debug_step_1_check_what_s_cached", "label": "Step 1: Check What's Cached", "file_type": "document", "source_file": "D:\\Development\\PixelTales(Image bug fixed)\\PixelTales\\docu\\OFFLINE_GAMES_EMPTY_DEBUG.md", "source_location": "L8"}, {"id": "docu_offline_games_empty_debug_codeblock_1", "label": "code:json ({)", "file_type": "document", "source_file": "D:\\Development\\PixelTales(Image bug fixed)\\PixelTales\\docu\\OFFLINE_GAMES_EMPTY_DEBUG.md", "source_location": "L17"}, {"id": "docu_offline_games_empty_debug_step_2_check_console_logs", "label": "Step 2: Check Console Logs", "file_type": "document", "source_file": "D:\\Development\\PixelTales(Image bug fixed)\\PixelTales\\docu\\OFFLINE_GAMES_EMPTY_DEBUG.md", "source_location": "L40"}, {"id": "docu_offline_games_empty_debug_codeblock_2", "label": "code:block2 (\ud83d\udd0d Looking for cached game with key: games_cache_game_data_55)", "file_type": "document", "source_file": "D:\\Development\\PixelTales(Image bug fixed)\\PixelTales\\docu\\OFFLINE_GAMES_EMPTY_DEBUG.md", "source_location": "L43"}, {"id": "docu_offline_games_empty_debug_step_3_identify_the_problem", "label": "Step 3: Identify the Problem", "file_type": "document", "source_file": "D:\\Development\\PixelTales(Image bug fixed)\\PixelTales\\docu\\OFFLINE_GAMES_EMPTY_DEBUG.md", "source_location": "L55"}, {"id": "docu_offline_games_empty_debug_scenario_a_cache_key_not_found", "label": "Scenario A: Cache Key Not Found", "file_type": "document", "source_file": "D:\\Development\\PixelTales(Image bug fixed)\\PixelTales\\docu\\OFFLINE_GAMES_EMPTY_DEBUG.md", "source_location": "L57"}, {"id": "docu_offline_games_empty_debug_codeblock_3", "label": "code:block3 (\ud83d\udd0d Looking for cached game with key: games_cache_game_data_55)", "file_type": "document", "source_file": "D:\\Development\\PixelTales(Image bug fixed)\\PixelTales\\docu\\OFFLINE_GAMES_EMPTY_DEBUG.md", "source_location": "L59"}, {"id": "docu_offline_games_empty_debug_scenario_b_data_structure_wrong", "label": "Scenario B: Data Structure Wrong", "file_type": "document", "source_file": "D:\\Development\\PixelTales(Image bug fixed)\\PixelTales\\docu\\OFFLINE_GAMES_EMPTY_DEBUG.md", "source_location": "L67"}, {"id": "docu_offline_games_empty_debug_codeblock_4", "label": "code:block4 (\u2705 Retrieved cached game data for game: 555)", "file_type": "document", "source_file": "D:\\Development\\PixelTales(Image bug fixed)\\PixelTales\\docu\\OFFLINE_GAMES_EMPTY_DEBUG.md", "source_location": "L69"}, {"id": "docu_offline_games_empty_debug_scenario_c_questions_empty_array", "label": "Scenario C: Questions Empty Array", "file_type": "document", "source_file": "D:\\Development\\PixelTales(Image bug fixed)\\PixelTales\\docu\\OFFLINE_GAMES_EMPTY_DEBUG.md", "source_location": "L77"}, {"id": "docu_offline_games_empty_debug_codeblock_5", "label": "code:block5 (\ud83d\udccb Questions in cache: [])", "file_type": "document", "source_file": "D:\\Development\\PixelTales(Image bug fixed)\\PixelTales\\docu\\OFFLINE_GAMES_EMPTY_DEBUG.md", "source_location": "L79"}, {"id": "docu_offline_games_empty_debug_what_to_share", "label": "\ud83d\udcdd What to Share", "file_type": "document", "source_file": "D:\\Development\\PixelTales(Image bug fixed)\\PixelTales\\docu\\OFFLINE_GAMES_EMPTY_DEBUG.md", "source_location": "L87"}, {"id": "docu_offline_games_empty_debug_quick_fixes_to_try", "label": "\ud83d\udd27 Quick Fixes to Try", "file_type": "document", "source_file": "D:\\Development\\PixelTales(Image bug fixed)\\PixelTales\\docu\\OFFLINE_GAMES_EMPTY_DEBUG.md", "source_location": "L97"}, {"id": "docu_offline_games_empty_debug_fix_1_recache_the_games", "label": "Fix 1: Recache the Games", "file_type": "document", "source_file": "D:\\Development\\PixelTales(Image bug fixed)\\PixelTales\\docu\\OFFLINE_GAMES_EMPTY_DEBUG.md", "source_location": "L99"}, {"id": "docu_offline_games_empty_debug_fix_2_check_browser_console_during_save", "label": "Fix 2: Check Browser Console During Save", "file_type": "document", "source_file": "D:\\Development\\PixelTales(Image bug fixed)\\PixelTales\\docu\\OFFLINE_GAMES_EMPTY_DEBUG.md", "source_location": "L107"}, {"id": "docu_offline_games_empty_debug_codeblock_6", "label": "code:block6 (\u2705 Cached game 557 (Word Search) questions)", "file_type": "document", "source_file": "D:\\Development\\PixelTales(Image bug fixed)\\PixelTales\\docu\\OFFLINE_GAMES_EMPTY_DEBUG.md", "source_location": "L109"}, {"id": "docu_offline_games_empty_debug_fix_3_manual_cache_check", "label": "Fix 3: Manual Cache Check", "file_type": "document", "source_file": "D:\\Development\\PixelTales(Image bug fixed)\\PixelTales\\docu\\OFFLINE_GAMES_EMPTY_DEBUG.md", "source_location": "L117"}, {"id": "docu_offline_games_empty_debug_codeblock_7", "label": "code:javascript (// Check if game 555 is cached)", "file_type": "document", "source_file": "D:\\Development\\PixelTales(Image bug fixed)\\PixelTales\\docu\\OFFLINE_GAMES_EMPTY_DEBUG.md", "source_location": "L119"}], "edges": [{"source": "d_development_pixeltales_image_bug_fixed_pixeltales_docu_offline_games_empty_debug_md", "target": "docu_offline_games_empty_debug_offline_games_empty_debug_guide", "relation": "contains", "confidence": "EXTRACTED", "source_file": "D:\\Development\\PixelTales(Image bug fixed)\\PixelTales\\docu\\OFFLINE_GAMES_EMPTY_DEBUG.md", "source_location": "L1", "weight": 1.0}, {"source": "docu_offline_games_empty_debug_offline_games_empty_debug_guide", "target": "docu_offline_games_empty_debug_issue", "relation": "contains", "confidence": "EXTRACTED", "source_file": "D:\\Development\\PixelTales(Image bug fixed)\\PixelTales\\docu\\OFFLINE_GAMES_EMPTY_DEBUG.md", "source_location": "L3", "weight": 1.0}, {"source": "docu_offline_games_empty_debug_offline_games_empty_debug_guide", "target": "docu_offline_games_empty_debug_debug_steps", "relation": "contains", "confidence": "EXTRACTED", "source_file": "D:\\Development\\PixelTales(Image bug fixed)\\PixelTales\\docu\\OFFLINE_GAMES_EMPTY_DEBUG.md", "source_location": "L6", "weight": 1.0}, {"source": "docu_offline_games_empty_debug_debug_steps", "target": "docu_offline_games_empty_debug_step_1_check_what_s_cached", "relation": "contains", "confidence": "EXTRACTED", "source_file": "D:\\Development\\PixelTales(Image bug fixed)\\PixelTales\\docu\\OFFLINE_GAMES_EMPTY_DEBUG.md", "source_location": "L8", "weight": 1.0}, {"source": "docu_offline_games_empty_debug_step_1_check_what_s_cached", "target": "docu_offline_games_empty_debug_codeblock_1", "relation": "contains", "confidence": "EXTRACTED", "source_file": "D:\\Development\\PixelTales(Image bug fixed)\\PixelTales\\docu\\OFFLINE_GAMES_EMPTY_DEBUG.md", "source_location": "L17", "weight": 1.0}, {"source": "docu_offline_games_empty_debug_debug_steps", "target": "docu_offline_games_empty_debug_step_2_check_console_logs", "relation": "contains", "confidence": "EXTRACTED", "source_file": "D:\\Development\\PixelTales(Image bug fixed)\\PixelTales\\docu\\OFFLINE_GAMES_EMPTY_DEBUG.md", "source_location": "L40", "weight": 1.0}, {"source": "docu_offline_games_empty_debug_step_2_check_console_logs", "target": "docu_offline_games_empty_debug_codeblock_2", "relation": "contains", "confidence": "EXTRACTED", "source_file": "D:\\Development\\PixelTales(Image bug fixed)\\PixelTales\\docu\\OFFLINE_GAMES_EMPTY_DEBUG.md", "source_location": "L43", "weight": 1.0}, {"source": "docu_offline_games_empty_debug_debug_steps", "target": "docu_offline_games_empty_debug_step_3_identify_the_problem", "relation": "contains", "confidence": "EXTRACTED", "source_file": "D:\\Development\\PixelTales(Image bug fixed)\\PixelTales\\docu\\OFFLINE_GAMES_EMPTY_DEBUG.md", "source_location": "L55", "weight": 1.0}, {"source": "docu_offline_games_empty_debug_step_3_identify_the_problem", "target": "docu_offline_games_empty_debug_scenario_a_cache_key_not_found", "relation": "contains", "confidence": "EXTRACTED", "source_file": "D:\\Development\\PixelTales(Image bug fixed)\\PixelTales\\docu\\OFFLINE_GAMES_EMPTY_DEBUG.md", "source_location": "L57", "weight": 1.0}, {"source": "docu_offline_games_empty_debug_scenario_a_cache_key_not_found", "target": "docu_offline_games_empty_debug_codeblock_3", "relation": "contains", "confidence": "EXTRACTED", "source_file": "D:\\Development\\PixelTales(Image bug fixed)\\PixelTales\\docu\\OFFLINE_GAMES_EMPTY_DEBUG.md", "source_location": "L59", "weight": 1.0}, {"source": "docu_offline_games_empty_debug_step_3_identify_the_problem", "target": "docu_offline_games_empty_debug_scenario_b_data_structure_wrong", "relation": "contains", "confidence": "EXTRACTED", "source_file": "D:\\Development\\PixelTales(Image bug fixed)\\PixelTales\\docu\\OFFLINE_GAMES_EMPTY_DEBUG.md", "source_location": "L67", "weight": 1.0}, {"source": "docu_offline_games_empty_debug_scenario_b_data_structure_wrong", "target": "docu_offline_games_empty_debug_codeblock_4", "relation": "contains", "confidence": "EXTRACTED", "source_file": "D:\\Development\\PixelTales(Image bug fixed)\\PixelTales\\docu\\OFFLINE_GAMES_EMPTY_DEBUG.md", "source_location": "L69", "weight": 1.0}, {"source": "docu_offline_games_empty_debug_step_3_identify_the_problem", "target": "docu_offline_games_empty_debug_scenario_c_questions_empty_array", "relation": "contains", "confidence": "EXTRACTED", "source_file": "D:\\Development\\PixelTales(Image bug fixed)\\PixelTales\\docu\\OFFLINE_GAMES_EMPTY_DEBUG.md", "source_location": "L77", "weight": 1.0}, {"source": "docu_offline_games_empty_debug_scenario_c_questions_empty_array", "target": "docu_offline_games_empty_debug_codeblock_5", "relation": "contains", "confidence": "EXTRACTED", "source_file": "D:\\Development\\PixelTales(Image bug fixed)\\PixelTales\\docu\\OFFLINE_GAMES_EMPTY_DEBUG.md", "source_location": "L79", "weight": 1.0}, {"source": "docu_offline_games_empty_debug_offline_games_empty_debug_guide", "target": "docu_offline_games_empty_debug_what_to_share", "relation": "contains", "confidence": "EXTRACTED", "source_file": "D:\\Development\\PixelTales(Image bug fixed)\\PixelTales\\docu\\OFFLINE_GAMES_EMPTY_DEBUG.md", "source_location": "L87", "weight": 1.0}, {"source": "docu_offline_games_empty_debug_offline_games_empty_debug_guide", "target": "docu_offline_games_empty_debug_quick_fixes_to_try", "relation": "contains", "confidence": "EXTRACTED", "source_file": "D:\\Development\\PixelTales(Image bug fixed)\\PixelTales\\docu\\OFFLINE_GAMES_EMPTY_DEBUG.md", "source_location": "L97", "weight": 1.0}, {"source": "docu_offline_games_empty_debug_quick_fixes_to_try", "target": "docu_offline_games_empty_debug_fix_1_recache_the_games", "relation": "contains", "confidence": "EXTRACTED", "source_file": "D:\\Development\\PixelTales(Image bug fixed)\\PixelTales\\docu\\OFFLINE_GAMES_EMPTY_DEBUG.md", "source_location": "L99", "weight": 1.0}, {"source": "docu_offline_games_empty_debug_quick_fixes_to_try", "target": "docu_offline_games_empty_debug_fix_2_check_browser_console_during_save", "relation": "contains", "confidence": "EXTRACTED", "source_file": "D:\\Development\\PixelTales(Image bug fixed)\\PixelTales\\docu\\OFFLINE_GAMES_EMPTY_DEBUG.md", "source_location": "L107", "weight": 1.0}, {"source": "docu_offline_games_empty_debug_fix_2_check_browser_console_during_save", "target": "docu_offline_games_empty_debug_codeblock_6", "relation": "contains", "confidence": "EXTRACTED", "source_file": "D:\\Development\\PixelTales(Image bug fixed)\\PixelTales\\docu\\OFFLINE_GAMES_EMPTY_DEBUG.md", "source_location": "L109", "weight": 1.0}, {"source": "docu_offline_games_empty_debug_quick_fixes_to_try", "target": "docu_offline_games_empty_debug_fix_3_manual_cache_check", "relation": "contains", "confidence": "EXTRACTED", "source_file": "D:\\Development\\PixelTales(Image bug fixed)\\PixelTales\\docu\\OFFLINE_GAMES_EMPTY_DEBUG.md", "source_location": "L117", "weight": 1.0}, {"source": "docu_offline_games_empty_debug_fix_3_manual_cache_check", "target": "docu_offline_games_empty_debug_codeblock_7", "relation": "contains", "confidence": "EXTRACTED", "source_file": "D:\\Development\\PixelTales(Image bug fixed)\\PixelTales\\docu\\OFFLINE_GAMES_EMPTY_DEBUG.md", "source_location": "L119", "weight": 1.0}], "input_tokens": 0, "output_tokens": 0}