{"nodes": [{"id": "d_development_pixeltales_image_bug_fixed_pixeltales_frontend_src_components_ui_upgradeprompt_tsx", "label": "UpgradePrompt.tsx", "file_type": "code", "source_file": "D:\\Development\\PixelTales(Image bug fixed)\\PixelTales\\frontend\\src\\components\\ui\\UpgradePrompt.tsx", "source_location": "L1"}, {"id": "ui_upgradeprompt_upgradepromptprops", "label": "UpgradePromptProps", "file_type": "code", "source_file": "D:\\Development\\PixelTales(Image bug fixed)\\PixelTales\\frontend\\src\\components\\ui\\UpgradePrompt.tsx", "source_location": "L12"}, {"id": "ui_upgradeprompt_upgradeprompt", "label": "UpgradePrompt()", "file_type": "code", "source_file": "D:\\Development\\PixelTales(Image bug fixed)\\PixelTales\\frontend\\src\\components\\ui\\UpgradePrompt.tsx", "source_location": "L19"}], "edges": [{"source": "d_development_pixeltales_image_bug_fixed_pixeltales_frontend_src_components_ui_upgradeprompt_tsx", "target": "framer_motion", "relation": "imports_from", "context": "import", "confidence": "EXTRACTED", "source_file": "D:\\Development\\PixelTales(Image bug fixed)\\PixelTales\\frontend\\src\\components\\ui\\UpgradePrompt.tsx", "source_location": "L6", "weight": 1.0}, {"source": "d_development_pixeltales_image_bug_fixed_pixeltales_frontend_src_components_ui_upgradeprompt_tsx", "target": "outline", "relation": "imports_from", "context": "import", "confidence": "EXTRACTED", "source_file": "D:\\Development\\PixelTales(Image bug fixed)\\PixelTales\\frontend\\src\\components\\ui\\UpgradePrompt.tsx", "source_location": "L7", "weight": 1.0}, {"source": "d_development_pixeltales_image_bug_fixed_pixeltales_frontend_src_components_ui_upgradeprompt_tsx", "target": "d_development_pixeltales_image_bug_fixed_pixeltales_frontend_src_services_featureaccess_service_ts", "relation": "imports_from", "context": "import", "confidence": "EXTRACTED", "source_file": "D:\\Development\\PixelTales(Image bug fixed)\\PixelTales\\frontend\\src\\components\\ui\\UpgradePrompt.tsx", "source_location": "L8", "weight": 1.0}, {"source": "d_development_pixeltales_image_bug_fixed_pixeltales_frontend_src_components_ui_upgradeprompt_tsx", "target": "services_featureaccess_service_featureaccessservice", "relation": "imports", "context": "import", "confidence": "EXTRACTED", "source_file": "D:\\Development\\PixelTales(Image bug fixed)\\PixelTales\\frontend\\src\\components\\ui\\UpgradePrompt.tsx", "source_location": "L8", "weight": 1.0}, {"source": "d_development_pixeltales_image_bug_fixed_pixeltales_frontend_src_components_ui_upgradeprompt_tsx", "target": "d_development_pixeltales_image_bug_fixed_pixeltales_frontend_src_stores_authstore_ts", "relation": "imports_from", "context": "import", "confidence": "EXTRACTED", "source_file": "D:\\Development\\PixelTales(Image bug fixed)\\PixelTales\\frontend\\src\\components\\ui\\UpgradePrompt.tsx", "source_location": "L9", "weight": 1.0}, {"source": "d_development_pixeltales_image_bug_fixed_pixeltales_frontend_src_components_ui_upgradeprompt_tsx", "target": "stores_authstore_useauthstore", "relation": "imports", "context": "import", "confidence": "EXTRACTED", "source_file": "D:\\Development\\PixelTales(Image bug fixed)\\PixelTales\\frontend\\src\\components\\ui\\UpgradePrompt.tsx", "source_location": "L9", "weight": 1.0}, {"source": "d_development_pixeltales_image_bug_fixed_pixeltales_frontend_src_components_ui_upgradeprompt_tsx", "target": "react_router_dom", "relation": "imports_from", "context": "import", "confidence": "EXTRACTED", "source_file": "D:\\Development\\PixelTales(Image bug fixed)\\PixelTales\\frontend\\src\\components\\ui\\UpgradePrompt.tsx", "source_location": "L10", "weight": 1.0}, {"source": "d_development_pixeltales_image_bug_fixed_pixeltales_frontend_src_components_ui_upgradeprompt_tsx", "target": "ui_upgradeprompt_upgradepromptprops", "relation": "contains", "confidence": "EXTRACTED", "source_file": "D:\\Development\\PixelTales(Image bug fixed)\\PixelTales\\frontend\\src\\components\\ui\\UpgradePrompt.tsx", "source_location": "L12", "weight": 1.0}, {"source": "d_development_pixeltales_image_bug_fixed_pixeltales_frontend_src_components_ui_upgradeprompt_tsx", "target": "ui_upgradeprompt_upgradeprompt", "relation": "contains", "confidence": "EXTRACTED", "source_file": "D:\\Development\\PixelTales(Image bug fixed)\\PixelTales\\frontend\\src\\components\\ui\\UpgradePrompt.tsx", "source_location": "L19", "weight": 1.0}], "raw_calls": [{"caller_nid": "ui_upgradeprompt_upgradeprompt", "callee": "useNavigate", "is_member_call": false, "source_file": "D:\\Development\\PixelTales(Image bug fixed)\\PixelTales\\frontend\\src\\components\\ui\\UpgradePrompt.tsx", "source_location": "L20"}, {"caller_nid": "ui_upgradeprompt_upgradeprompt", "callee": "useAuthStore", "is_member_call": false, "source_file": "D:\\Development\\PixelTales(Image bug fixed)\\PixelTales\\frontend\\src\\components\\ui\\UpgradePrompt.tsx", "source_location": "L21"}, {"caller_nid": "ui_upgradeprompt_upgradeprompt", "callee": "getPremiumFeatures", "is_member_call": true, "source_file": "D:\\Development\\PixelTales(Image bug fixed)\\PixelTales\\frontend\\src\\components\\ui\\UpgradePrompt.tsx", "source_location": "L23"}, {"caller_nid": "ui_upgradeprompt_upgradeprompt", "callee": "getTitle", "is_member_call": false, "source_file": "D:\\Development\\PixelTales(Image bug fixed)\\PixelTales\\frontend\\src\\components\\ui\\UpgradePrompt.tsx", "source_location": "L89"}, {"caller_nid": "ui_upgradeprompt_upgradeprompt", "callee": "getMessage", "is_member_call": false, "source_file": "D:\\Development\\PixelTales(Image bug fixed)\\PixelTales\\frontend\\src\\components\\ui\\UpgradePrompt.tsx", "source_location": "L91"}, {"caller_nid": "ui_upgradeprompt_upgradeprompt", "callee": "map", "is_member_call": true, "source_file": "D:\\Development\\PixelTales(Image bug fixed)\\PixelTales\\frontend\\src\\components\\ui\\UpgradePrompt.tsx", "source_location": "L100"}, {"caller_nid": "ui_upgradeprompt_upgradeprompt", "callee": "slice", "is_member_call": true, "source_file": "D:\\Development\\PixelTales(Image bug fixed)\\PixelTales\\frontend\\src\\components\\ui\\UpgradePrompt.tsx", "source_location": "L100"}]}