{"nodes": [{"id": "d_development_pixeltales_image_bug_fixed_pixeltales_docu_offline_story_fix_md", "label": "OFFLINE_STORY_FIX.md", "file_type": "document", "source_file": "D:\\Development\\PixelTales(Image bug fixed)\\PixelTales\\docu\\OFFLINE_STORY_FIX.md", "source_location": "L1"}, {"id": "docu_offline_story_fix_offline_story_loading_fix", "label": "Offline Story Loading Fix", "file_type": "document", "source_file": "D:\\Development\\PixelTales(Image bug fixed)\\PixelTales\\docu\\OFFLINE_STORY_FIX.md", "source_location": "L1"}, {"id": "docu_offline_story_fix_problem", "label": "\ud83d\udc1b Problem", "file_type": "document", "source_file": "D:\\Development\\PixelTales(Image bug fixed)\\PixelTales\\docu\\OFFLINE_STORY_FIX.md", "source_location": "L3"}, {"id": "docu_offline_story_fix_root_cause", "label": "\ud83d\udd0d Root Cause", "file_type": "document", "source_file": "D:\\Development\\PixelTales(Image bug fixed)\\PixelTales\\docu\\OFFLINE_STORY_FIX.md", "source_location": "L6"}, {"id": "docu_offline_story_fix_original_code_line_542_546", "label": "Original Code (Line 542-546):", "file_type": "document", "source_file": "D:\\Development\\PixelTales(Image bug fixed)\\PixelTales\\docu\\OFFLINE_STORY_FIX.md", "source_location": "L9"}, {"id": "docu_offline_story_fix_codeblock_1", "label": "code:typescript (getStory: (id: string) => {)", "file_type": "document", "source_file": "D:\\Development\\PixelTales(Image bug fixed)\\PixelTales\\docu\\OFFLINE_STORY_FIX.md", "source_location": "L10"}, {"id": "docu_offline_story_fix_solution_applied", "label": "\u2705 Solution Applied", "file_type": "document", "source_file": "D:\\Development\\PixelTales(Image bug fixed)\\PixelTales\\docu\\OFFLINE_STORY_FIX.md", "source_location": "L22"}, {"id": "docu_offline_story_fix_1_fixed_getstory_function", "label": "1. **Fixed `getStory` Function**", "file_type": "document", "source_file": "D:\\Development\\PixelTales(Image bug fixed)\\PixelTales\\docu\\OFFLINE_STORY_FIX.md", "source_location": "L24"}, {"id": "docu_offline_story_fix_codeblock_2", "label": "code:typescript (getStory: (id: string) => {)", "file_type": "document", "source_file": "D:\\Development\\PixelTales(Image bug fixed)\\PixelTales\\docu\\OFFLINE_STORY_FIX.md", "source_location": "L27"}, {"id": "docu_offline_story_fix_2_enhanced_isstorysavedoffline_function", "label": "2. **Enhanced `isStorySavedOffline` Function**", "file_type": "document", "source_file": "D:\\Development\\PixelTales(Image bug fixed)\\PixelTales\\docu\\OFFLINE_STORY_FIX.md", "source_location": "L42"}, {"id": "docu_offline_story_fix_codeblock_3", "label": "code:typescript (isStorySavedOffline: (storyId: string) => {)", "file_type": "document", "source_file": "D:\\Development\\PixelTales(Image bug fixed)\\PixelTales\\docu\\OFFLINE_STORY_FIX.md", "source_location": "L45"}, {"id": "docu_offline_story_fix_3_enhanced_removeofflinestory_function", "label": "3. **Enhanced `removeOfflineStory` Function**", "file_type": "document", "source_file": "D:\\Development\\PixelTales(Image bug fixed)\\PixelTales\\docu\\OFFLINE_STORY_FIX.md", "source_location": "L62"}, {"id": "docu_offline_story_fix_codeblock_4", "label": "code:typescript (removeOfflineStory: (storyId: string) => {)", "file_type": "document", "source_file": "D:\\Development\\PixelTales(Image bug fixed)\\PixelTales\\docu\\OFFLINE_STORY_FIX.md", "source_location": "L65"}, {"id": "docu_offline_story_fix_4_enhanced_savestoryoffline_function", "label": "4. **Enhanced `saveStoryOffline` Function**", "file_type": "document", "source_file": "D:\\Development\\PixelTales(Image bug fixed)\\PixelTales\\docu\\OFFLINE_STORY_FIX.md", "source_location": "L93"}, {"id": "docu_offline_story_fix_codeblock_5", "label": "code:typescript (saveStoryOffline: (story: Story) => {)", "file_type": "document", "source_file": "D:\\Development\\PixelTales(Image bug fixed)\\PixelTales\\docu\\OFFLINE_STORY_FIX.md", "source_location": "L96"}, {"id": "docu_offline_story_fix_files_modified", "label": "\ud83d\udccb Files Modified", "file_type": "document", "source_file": "D:\\Development\\PixelTales(Image bug fixed)\\PixelTales\\docu\\OFFLINE_STORY_FIX.md", "source_location": "L132"}, {"id": "docu_offline_story_fix_how_to_test", "label": "\ud83e\uddea How to Test", "file_type": "document", "source_file": "D:\\Development\\PixelTales(Image bug fixed)\\PixelTales\\docu\\OFFLINE_STORY_FIX.md", "source_location": "L139"}, {"id": "docu_offline_story_fix_test_1_save_and_load_other_user_s_story", "label": "Test 1: Save and Load Other User's Story", "file_type": "document", "source_file": "D:\\Development\\PixelTales(Image bug fixed)\\PixelTales\\docu\\OFFLINE_STORY_FIX.md", "source_location": "L141"}, {"id": "docu_offline_story_fix_test_2_verify_offline_icon_shows_correctly", "label": "Test 2: Verify Offline Icon Shows Correctly", "file_type": "document", "source_file": "D:\\Development\\PixelTales(Image bug fixed)\\PixelTales\\docu\\OFFLINE_STORY_FIX.md", "source_location": "L152"}, {"id": "docu_offline_story_fix_test_3_remove_offline_story", "label": "Test 3: Remove Offline Story", "file_type": "document", "source_file": "D:\\Development\\PixelTales(Image bug fixed)\\PixelTales\\docu\\OFFLINE_STORY_FIX.md", "source_location": "L157"}, {"id": "docu_offline_story_fix_test_4_duplicate_prevention", "label": "Test 4: Duplicate Prevention", "file_type": "document", "source_file": "D:\\Development\\PixelTales(Image bug fixed)\\PixelTales\\docu\\OFFLINE_STORY_FIX.md", "source_location": "L164"}, {"id": "docu_offline_story_fix_benefits", "label": "\u2728 Benefits", "file_type": "document", "source_file": "D:\\Development\\PixelTales(Image bug fixed)\\PixelTales\\docu\\OFFLINE_STORY_FIX.md", "source_location": "L170"}, {"id": "docu_offline_story_fix_before_fix", "label": "Before Fix:", "file_type": "document", "source_file": "D:\\Development\\PixelTales(Image bug fixed)\\PixelTales\\docu\\OFFLINE_STORY_FIX.md", "source_location": "L172"}, {"id": "docu_offline_story_fix_after_fix", "label": "After Fix:", "file_type": "document", "source_file": "D:\\Development\\PixelTales(Image bug fixed)\\PixelTales\\docu\\OFFLINE_STORY_FIX.md", "source_location": "L177"}, {"id": "docu_offline_story_fix_data_structure", "label": "\ud83d\udd04 Data Structure", "file_type": "document", "source_file": "D:\\Development\\PixelTales(Image bug fixed)\\PixelTales\\docu\\OFFLINE_STORY_FIX.md", "source_location": "L185"}, {"id": "docu_offline_story_fix_user_library_structure", "label": "User Library Structure:", "file_type": "document", "source_file": "D:\\Development\\PixelTales(Image bug fixed)\\PixelTales\\docu\\OFFLINE_STORY_FIX.md", "source_location": "L187"}, {"id": "docu_offline_story_fix_codeblock_6", "label": "code:typescript (interface UserLibrary {)", "file_type": "document", "source_file": "D:\\Development\\PixelTales(Image bug fixed)\\PixelTales\\docu\\OFFLINE_STORY_FIX.md", "source_location": "L188"}, {"id": "docu_offline_story_fix_story_id_formats", "label": "Story ID Formats:", "file_type": "document", "source_file": "D:\\Development\\PixelTales(Image bug fixed)\\PixelTales\\docu\\OFFLINE_STORY_FIX.md", "source_location": "L196"}], "edges": [{"source": "d_development_pixeltales_image_bug_fixed_pixeltales_docu_offline_story_fix_md", "target": "docu_offline_story_fix_offline_story_loading_fix", "relation": "contains", "confidence": "EXTRACTED", "source_file": "D:\\Development\\PixelTales(Image bug fixed)\\PixelTales\\docu\\OFFLINE_STORY_FIX.md", "source_location": "L1", "weight": 1.0}, {"source": "docu_offline_story_fix_offline_story_loading_fix", "target": "docu_offline_story_fix_problem", "relation": "contains", "confidence": "EXTRACTED", "source_file": "D:\\Development\\PixelTales(Image bug fixed)\\PixelTales\\docu\\OFFLINE_STORY_FIX.md", "source_location": "L3", "weight": 1.0}, {"source": "docu_offline_story_fix_offline_story_loading_fix", "target": "docu_offline_story_fix_root_cause", "relation": "contains", "confidence": "EXTRACTED", "source_file": "D:\\Development\\PixelTales(Image bug fixed)\\PixelTales\\docu\\OFFLINE_STORY_FIX.md", "source_location": "L6", "weight": 1.0}, {"source": "docu_offline_story_fix_root_cause", "target": "docu_offline_story_fix_original_code_line_542_546", "relation": "contains", "confidence": "EXTRACTED", "source_file": "D:\\Development\\PixelTales(Image bug fixed)\\PixelTales\\docu\\OFFLINE_STORY_FIX.md", "source_location": "L9", "weight": 1.0}, {"source": "docu_offline_story_fix_original_code_line_542_546", "target": "docu_offline_story_fix_codeblock_1", "relation": "contains", "confidence": "EXTRACTED", "source_file": "D:\\Development\\PixelTales(Image bug fixed)\\PixelTales\\docu\\OFFLINE_STORY_FIX.md", "source_location": "L10", "weight": 1.0}, {"source": "docu_offline_story_fix_offline_story_loading_fix", "target": "docu_offline_story_fix_solution_applied", "relation": "contains", "confidence": "EXTRACTED", "source_file": "D:\\Development\\PixelTales(Image bug fixed)\\PixelTales\\docu\\OFFLINE_STORY_FIX.md", "source_location": "L22", "weight": 1.0}, {"source": "docu_offline_story_fix_solution_applied", "target": "docu_offline_story_fix_1_fixed_getstory_function", "relation": "contains", "confidence": "EXTRACTED", "source_file": "D:\\Development\\PixelTales(Image bug fixed)\\PixelTales\\docu\\OFFLINE_STORY_FIX.md", "source_location": "L24", "weight": 1.0}, {"source": "docu_offline_story_fix_1_fixed_getstory_function", "target": "docu_offline_story_fix_codeblock_2", "relation": "contains", "confidence": "EXTRACTED", "source_file": "D:\\Development\\PixelTales(Image bug fixed)\\PixelTales\\docu\\OFFLINE_STORY_FIX.md", "source_location": "L27", "weight": 1.0}, {"source": "docu_offline_story_fix_solution_applied", "target": "docu_offline_story_fix_2_enhanced_isstorysavedoffline_function", "relation": "contains", "confidence": "EXTRACTED", "source_file": "D:\\Development\\PixelTales(Image bug fixed)\\PixelTales\\docu\\OFFLINE_STORY_FIX.md", "source_location": "L42", "weight": 1.0}, {"source": "docu_offline_story_fix_2_enhanced_isstorysavedoffline_function", "target": "docu_offline_story_fix_codeblock_3", "relation": "contains", "confidence": "EXTRACTED", "source_file": "D:\\Development\\PixelTales(Image bug fixed)\\PixelTales\\docu\\OFFLINE_STORY_FIX.md", "source_location": "L45", "weight": 1.0}, {"source": "docu_offline_story_fix_solution_applied", "target": "docu_offline_story_fix_3_enhanced_removeofflinestory_function", "relation": "contains", "confidence": "EXTRACTED", "source_file": "D:\\Development\\PixelTales(Image bug fixed)\\PixelTales\\docu\\OFFLINE_STORY_FIX.md", "source_location": "L62", "weight": 1.0}, {"source": "docu_offline_story_fix_3_enhanced_removeofflinestory_function", "target": "docu_offline_story_fix_codeblock_4", "relation": "contains", "confidence": "EXTRACTED", "source_file": "D:\\Development\\PixelTales(Image bug fixed)\\PixelTales\\docu\\OFFLINE_STORY_FIX.md", "source_location": "L65", "weight": 1.0}, {"source": "docu_offline_story_fix_solution_applied", "target": "docu_offline_story_fix_4_enhanced_savestoryoffline_function", "relation": "contains", "confidence": "EXTRACTED", "source_file": "D:\\Development\\PixelTales(Image bug fixed)\\PixelTales\\docu\\OFFLINE_STORY_FIX.md", "source_location": "L93", "weight": 1.0}, {"source": "docu_offline_story_fix_4_enhanced_savestoryoffline_function", "target": "docu_offline_story_fix_codeblock_5", "relation": "contains", "confidence": "EXTRACTED", "source_file": "D:\\Development\\PixelTales(Image bug fixed)\\PixelTales\\docu\\OFFLINE_STORY_FIX.md", "source_location": "L96", "weight": 1.0}, {"source": "docu_offline_story_fix_offline_story_loading_fix", "target": "docu_offline_story_fix_files_modified", "relation": "contains", "confidence": "EXTRACTED", "source_file": "D:\\Development\\PixelTales(Image bug fixed)\\PixelTales\\docu\\OFFLINE_STORY_FIX.md", "source_location": "L132", "weight": 1.0}, {"source": "docu_offline_story_fix_offline_story_loading_fix", "target": "docu_offline_story_fix_how_to_test", "relation": "contains", "confidence": "EXTRACTED", "source_file": "D:\\Development\\PixelTales(Image bug fixed)\\PixelTales\\docu\\OFFLINE_STORY_FIX.md", "source_location": "L139", "weight": 1.0}, {"source": "docu_offline_story_fix_how_to_test", "target": "docu_offline_story_fix_test_1_save_and_load_other_user_s_story", "relation": "contains", "confidence": "EXTRACTED", "source_file": "D:\\Development\\PixelTales(Image bug fixed)\\PixelTales\\docu\\OFFLINE_STORY_FIX.md", "source_location": "L141", "weight": 1.0}, {"source": "docu_offline_story_fix_how_to_test", "target": "docu_offline_story_fix_test_2_verify_offline_icon_shows_correctly", "relation": "contains", "confidence": "EXTRACTED", "source_file": "D:\\Development\\PixelTales(Image bug fixed)\\PixelTales\\docu\\OFFLINE_STORY_FIX.md", "source_location": "L152", "weight": 1.0}, {"source": "docu_offline_story_fix_how_to_test", "target": "docu_offline_story_fix_test_3_remove_offline_story", "relation": "contains", "confidence": "EXTRACTED", "source_file": "D:\\Development\\PixelTales(Image bug fixed)\\PixelTales\\docu\\OFFLINE_STORY_FIX.md", "source_location": "L157", "weight": 1.0}, {"source": "docu_offline_story_fix_how_to_test", "target": "docu_offline_story_fix_test_4_duplicate_prevention", "relation": "contains", "confidence": "EXTRACTED", "source_file": "D:\\Development\\PixelTales(Image bug fixed)\\PixelTales\\docu\\OFFLINE_STORY_FIX.md", "source_location": "L164", "weight": 1.0}, {"source": "docu_offline_story_fix_offline_story_loading_fix", "target": "docu_offline_story_fix_benefits", "relation": "contains", "confidence": "EXTRACTED", "source_file": "D:\\Development\\PixelTales(Image bug fixed)\\PixelTales\\docu\\OFFLINE_STORY_FIX.md", "source_location": "L170", "weight": 1.0}, {"source": "docu_offline_story_fix_benefits", "target": "docu_offline_story_fix_before_fix", "relation": "contains", "confidence": "EXTRACTED", "source_file": "D:\\Development\\PixelTales(Image bug fixed)\\PixelTales\\docu\\OFFLINE_STORY_FIX.md", "source_location": "L172", "weight": 1.0}, {"source": "docu_offline_story_fix_benefits", "target": "docu_offline_story_fix_after_fix", "relation": "contains", "confidence": "EXTRACTED", "source_file": "D:\\Development\\PixelTales(Image bug fixed)\\PixelTales\\docu\\OFFLINE_STORY_FIX.md", "source_location": "L177", "weight": 1.0}, {"source": "docu_offline_story_fix_offline_story_loading_fix", "target": "docu_offline_story_fix_data_structure", "relation": "contains", "confidence": "EXTRACTED", "source_file": "D:\\Development\\PixelTales(Image bug fixed)\\PixelTales\\docu\\OFFLINE_STORY_FIX.md", "source_location": "L185", "weight": 1.0}, {"source": "docu_offline_story_fix_data_structure", "target": "docu_offline_story_fix_user_library_structure", "relation": "contains", "confidence": "EXTRACTED", "source_file": "D:\\Development\\PixelTales(Image bug fixed)\\PixelTales\\docu\\OFFLINE_STORY_FIX.md", "source_location": "L187", "weight": 1.0}, {"source": "docu_offline_story_fix_user_library_structure", "target": "docu_offline_story_fix_codeblock_6", "relation": "contains", "confidence": "EXTRACTED", "source_file": "D:\\Development\\PixelTales(Image bug fixed)\\PixelTales\\docu\\OFFLINE_STORY_FIX.md", "source_location": "L188", "weight": 1.0}, {"source": "docu_offline_story_fix_data_structure", "target": "docu_offline_story_fix_story_id_formats", "relation": "contains", "confidence": "EXTRACTED", "source_file": "D:\\Development\\PixelTales(Image bug fixed)\\PixelTales\\docu\\OFFLINE_STORY_FIX.md", "source_location": "L196", "weight": 1.0}], "input_tokens": 0, "output_tokens": 0}