{"nodes": [{"id": "d_development_pixeltales_image_bug_fixed_pixeltales_frontend_src_services_soundservice_ts", "label": "soundService.ts", "file_type": "code", "source_file": "D:\\Development\\PixelTales(Image bug fixed)\\PixelTales\\frontend\\src\\services\\soundService.ts", "source_location": "L1"}, {"id": "services_soundservice_soundtype", "label": "SoundType", "file_type": "code", "source_file": "D:\\Development\\PixelTales(Image bug fixed)\\PixelTales\\frontend\\src\\services\\soundService.ts", "source_location": "L6"}, {"id": "services_soundservice_backgroundmusictrack", "label": "BackgroundMusicTrack", "file_type": "code", "source_file": "D:\\Development\\PixelTales(Image bug fixed)\\PixelTales\\frontend\\src\\services\\soundService.ts", "source_location": "L41"}, {"id": "services_soundservice_soundconfig", "label": "SoundConfig", "file_type": "code", "source_file": "D:\\Development\\PixelTales(Image bug fixed)\\PixelTales\\frontend\\src\\services\\soundService.ts", "source_location": "L49"}, {"id": "services_soundservice_soundservice", "label": "SoundService", "file_type": "code", "source_file": "D:\\Development\\PixelTales(Image bug fixed)\\PixelTales\\frontend\\src\\services\\soundService.ts", "source_location": "L55"}, {"id": "services_soundservice_soundservice_constructor", "label": ".constructor()", "file_type": "code", "source_file": "D:\\Development\\PixelTales(Image bug fixed)\\PixelTales\\frontend\\src\\services\\soundService.ts", "source_location": "L105"}, {"id": "services_soundservice_soundservice_preloadcommonsounds", "label": ".preloadCommonSounds()", "file_type": "code", "source_file": "D:\\Development\\PixelTales(Image bug fixed)\\PixelTales\\frontend\\src\\services\\soundService.ts", "source_location": "L137"}, {"id": "services_soundservice_soundservice_loadsound", "label": ".loadSound()", "file_type": "code", "source_file": "D:\\Development\\PixelTales(Image bug fixed)\\PixelTales\\frontend\\src\\services\\soundService.ts", "source_location": "L153"}, {"id": "services_soundservice_soundservice_playsound", "label": ".playSound()", "file_type": "code", "source_file": "D:\\Development\\PixelTales(Image bug fixed)\\PixelTales\\frontend\\src\\services\\soundService.ts", "source_location": "L173"}, {"id": "services_soundservice_soundservice_stopsound", "label": ".stopSound()", "file_type": "code", "source_file": "D:\\Development\\PixelTales(Image bug fixed)\\PixelTales\\frontend\\src\\services\\soundService.ts", "source_location": "L219"}, {"id": "services_soundservice_soundservice_stopallsounds", "label": ".stopAllSounds()", "file_type": "code", "source_file": "D:\\Development\\PixelTales(Image bug fixed)\\PixelTales\\frontend\\src\\services\\soundService.ts", "source_location": "L230"}, {"id": "services_soundservice_soundservice_setenabled", "label": ".setEnabled()", "file_type": "code", "source_file": "D:\\Development\\PixelTales(Image bug fixed)\\PixelTales\\frontend\\src\\services\\soundService.ts", "source_location": "L240"}, {"id": "services_soundservice_soundservice_isenabled", "label": ".isEnabled()", "file_type": "code", "source_file": "D:\\Development\\PixelTales(Image bug fixed)\\PixelTales\\frontend\\src\\services\\soundService.ts", "source_location": "L252"}, {"id": "services_soundservice_soundservice_setglobalvolume", "label": ".setGlobalVolume()", "file_type": "code", "source_file": "D:\\Development\\PixelTales(Image bug fixed)\\PixelTales\\frontend\\src\\services\\soundService.ts", "source_location": "L259"}, {"id": "services_soundservice_soundservice_getglobalvolume", "label": ".getGlobalVolume()", "file_type": "code", "source_file": "D:\\Development\\PixelTales(Image bug fixed)\\PixelTales\\frontend\\src\\services\\soundService.ts", "source_location": "L273"}, {"id": "services_soundservice_soundservice_preload", "label": ".preload()", "file_type": "code", "source_file": "D:\\Development\\PixelTales(Image bug fixed)\\PixelTales\\frontend\\src\\services\\soundService.ts", "source_location": "L280"}, {"id": "services_soundservice_soundservice_preloadsounds", "label": ".preloadSounds()", "file_type": "code", "source_file": "D:\\Development\\PixelTales(Image bug fixed)\\PixelTales\\frontend\\src\\services\\soundService.ts", "source_location": "L289"}, {"id": "services_soundservice_soundservice_playsuccesswithhaptic", "label": ".playSuccessWithHaptic()", "file_type": "code", "source_file": "D:\\Development\\PixelTales(Image bug fixed)\\PixelTales\\frontend\\src\\services\\soundService.ts", "source_location": "L296"}, {"id": "services_soundservice_soundservice_playerrorwithhaptic", "label": ".playErrorWithHaptic()", "file_type": "code", "source_file": "D:\\Development\\PixelTales(Image bug fixed)\\PixelTales\\frontend\\src\\services\\soundService.ts", "source_location": "L304"}, {"id": "services_soundservice_soundservice_triggerhaptic", "label": ".triggerHaptic()", "file_type": "code", "source_file": "D:\\Development\\PixelTales(Image bug fixed)\\PixelTales\\frontend\\src\\services\\soundService.ts", "source_location": "L312"}, {"id": "services_soundservice_soundservice_playhaptic", "label": ".playHaptic()", "file_type": "code", "source_file": "D:\\Development\\PixelTales(Image bug fixed)\\PixelTales\\frontend\\src\\services\\soundService.ts", "source_location": "L322"}, {"id": "services_soundservice_soundservice_initbackgroundmusic", "label": ".initBackgroundMusic()", "file_type": "code", "source_file": "D:\\Development\\PixelTales(Image bug fixed)\\PixelTales\\frontend\\src\\services\\soundService.ts", "source_location": "L329"}, {"id": "services_soundservice_soundservice_switchtorandomtrack", "label": ".switchToRandomTrack()", "file_type": "code", "source_file": "D:\\Development\\PixelTales(Image bug fixed)\\PixelTales\\frontend\\src\\services\\soundService.ts", "source_location": "L398"}, {"id": "services_soundservice_soundservice_getrandomtrack", "label": ".getRandomTrack()", "file_type": "code", "source_file": "D:\\Development\\PixelTales(Image bug fixed)\\PixelTales\\frontend\\src\\services\\soundService.ts", "source_location": "L429"}, {"id": "services_soundservice_soundservice_gettracktoplay", "label": ".getTrackToPlay()", "file_type": "code", "source_file": "D:\\Development\\PixelTales(Image bug fixed)\\PixelTales\\frontend\\src\\services\\soundService.ts", "source_location": "L446"}, {"id": "services_soundservice_soundservice_startbackgroundmusic", "label": ".startBackgroundMusic()", "file_type": "code", "source_file": "D:\\Development\\PixelTales(Image bug fixed)\\PixelTales\\frontend\\src\\services\\soundService.ts", "source_location": "L456"}, {"id": "services_soundservice_soundservice_stopbackgroundmusic", "label": ".stopBackgroundMusic()", "file_type": "code", "source_file": "D:\\Development\\PixelTales(Image bug fixed)\\PixelTales\\frontend\\src\\services\\soundService.ts", "source_location": "L495"}, {"id": "services_soundservice_soundservice_pausebackgroundmusic", "label": ".pauseBackgroundMusic()", "file_type": "code", "source_file": "D:\\Development\\PixelTales(Image bug fixed)\\PixelTales\\frontend\\src\\services\\soundService.ts", "source_location": "L509"}, {"id": "services_soundservice_soundservice_resumebackgroundmusic", "label": ".resumeBackgroundMusic()", "file_type": "code", "source_file": "D:\\Development\\PixelTales(Image bug fixed)\\PixelTales\\frontend\\src\\services\\soundService.ts", "source_location": "L518"}, {"id": "services_soundservice_soundservice_fadeinmusic", "label": ".fadeInMusic()", "file_type": "code", "source_file": "D:\\Development\\PixelTales(Image bug fixed)\\PixelTales\\frontend\\src\\services\\soundService.ts", "source_location": "L532"}, {"id": "services_soundservice_soundservice_fadeoutmusic", "label": ".fadeOutMusic()", "file_type": "code", "source_file": "D:\\Development\\PixelTales(Image bug fixed)\\PixelTales\\frontend\\src\\services\\soundService.ts", "source_location": "L558"}, {"id": "services_soundservice_soundservice_setbackgroundmusicvolume", "label": ".setBackgroundMusicVolume()", "file_type": "code", "source_file": "D:\\Development\\PixelTales(Image bug fixed)\\PixelTales\\frontend\\src\\services\\soundService.ts", "source_location": "L590"}, {"id": "services_soundservice_soundservice_getbackgroundmusicvolume", "label": ".getBackgroundMusicVolume()", "file_type": "code", "source_file": "D:\\Development\\PixelTales(Image bug fixed)\\PixelTales\\frontend\\src\\services\\soundService.ts", "source_location": "L602"}, {"id": "services_soundservice_soundservice_setbackgroundmusicenabled", "label": ".setBackgroundMusicEnabled()", "file_type": "code", "source_file": "D:\\Development\\PixelTales(Image bug fixed)\\PixelTales\\frontend\\src\\services\\soundService.ts", "source_location": "L609"}, {"id": "services_soundservice_soundservice_isbackgroundmusicenabled", "label": ".isBackgroundMusicEnabled()", "file_type": "code", "source_file": "D:\\Development\\PixelTales(Image bug fixed)\\PixelTales\\frontend\\src\\services\\soundService.ts", "source_location": "L621"}, {"id": "services_soundservice_soundservice_isbackgroundmusicplaying", "label": ".isBackgroundMusicPlaying()", "file_type": "code", "source_file": "D:\\Development\\PixelTales(Image bug fixed)\\PixelTales\\frontend\\src\\services\\soundService.ts", "source_location": "L628"}, {"id": "services_soundservice_soundservice_setbackgroundmusictrack", "label": ".setBackgroundMusicTrack()", "file_type": "code", "source_file": "D:\\Development\\PixelTales(Image bug fixed)\\PixelTales\\frontend\\src\\services\\soundService.ts", "source_location": "L635"}, {"id": "services_soundservice_soundservice_getselectedmusictrack", "label": ".getSelectedMusicTrack()", "file_type": "code", "source_file": "D:\\Development\\PixelTales(Image bug fixed)\\PixelTales\\frontend\\src\\services\\soundService.ts", "source_location": "L651"}, {"id": "services_soundservice_soundservice_getavailabletracks", "label": ".getAvailableTracks()", "file_type": "code", "source_file": "D:\\Development\\PixelTales(Image bug fixed)\\PixelTales\\frontend\\src\\services\\soundService.ts", "source_location": "L658"}, {"id": "services_soundservice_soundservice_getcurrenttrackname", "label": ".getCurrentTrackName()", "file_type": "code", "source_file": "D:\\Development\\PixelTales(Image bug fixed)\\PixelTales\\frontend\\src\\services\\soundService.ts", "source_location": "L665"}, {"id": "services_soundservice_soundservice_gettrackdisplayname", "label": ".getTrackDisplayName()", "file_type": "code", "source_file": "D:\\Development\\PixelTales(Image bug fixed)\\PixelTales\\frontend\\src\\services\\soundService.ts", "source_location": "L683"}], "edges": [{"source": "d_development_pixeltales_image_bug_fixed_pixeltales_frontend_src_services_soundservice_ts", "target": "services_soundservice_soundtype", "relation": "contains", "confidence": "EXTRACTED", "source_file": "D:\\Development\\PixelTales(Image bug fixed)\\PixelTales\\frontend\\src\\services\\soundService.ts", "source_location": "L6", "weight": 1.0}, {"source": "d_development_pixeltales_image_bug_fixed_pixeltales_frontend_src_services_soundservice_ts", "target": "services_soundservice_backgroundmusictrack", "relation": "contains", "confidence": "EXTRACTED", "source_file": "D:\\Development\\PixelTales(Image bug fixed)\\PixelTales\\frontend\\src\\services\\soundService.ts", "source_location": "L41", "weight": 1.0}, {"source": "d_development_pixeltales_image_bug_fixed_pixeltales_frontend_src_services_soundservice_ts", "target": "services_soundservice_soundconfig", "relation": "contains", "confidence": "EXTRACTED", "source_file": "D:\\Development\\PixelTales(Image bug fixed)\\PixelTales\\frontend\\src\\services\\soundService.ts", "source_location": "L49", "weight": 1.0}, {"source": "d_development_pixeltales_image_bug_fixed_pixeltales_frontend_src_services_soundservice_ts", "target": "services_soundservice_soundservice", "relation": "contains", "confidence": "EXTRACTED", "source_file": "D:\\Development\\PixelTales(Image bug fixed)\\PixelTales\\frontend\\src\\services\\soundService.ts", "source_location": "L55", "weight": 1.0}, {"source": "services_soundservice_soundservice", "target": "services_soundservice_soundservice_constructor", "relation": "method", "confidence": "EXTRACTED", "source_file": "D:\\Development\\PixelTales(Image bug fixed)\\PixelTales\\frontend\\src\\services\\soundService.ts", "source_location": "L105", "weight": 1.0}, {"source": "services_soundservice_soundservice", "target": "services_soundservice_soundservice_preloadcommonsounds", "relation": "method", "confidence": "EXTRACTED", "source_file": "D:\\Development\\PixelTales(Image bug fixed)\\PixelTales\\frontend\\src\\services\\soundService.ts", "source_location": "L137", "weight": 1.0}, {"source": "services_soundservice_soundservice", "target": "services_soundservice_soundservice_loadsound", "relation": "method", "confidence": "EXTRACTED", "source_file": "D:\\Development\\PixelTales(Image bug fixed)\\PixelTales\\frontend\\src\\services\\soundService.ts", "source_location": "L153", "weight": 1.0}, {"source": "services_soundservice_soundservice", "target": "services_soundservice_soundservice_playsound", "relation": "method", "confidence": "EXTRACTED", "source_file": "D:\\Development\\PixelTales(Image bug fixed)\\PixelTales\\frontend\\src\\services\\soundService.ts", "source_location": "L173", "weight": 1.0}, {"source": "services_soundservice_soundservice", "target": "services_soundservice_soundservice_stopsound", "relation": "method", "confidence": "EXTRACTED", "source_file": "D:\\Development\\PixelTales(Image bug fixed)\\PixelTales\\frontend\\src\\services\\soundService.ts", "source_location": "L219", "weight": 1.0}, {"source": "services_soundservice_soundservice", "target": "services_soundservice_soundservice_stopallsounds", "relation": "method", "confidence": "EXTRACTED", "source_file": "D:\\Development\\PixelTales(Image bug fixed)\\PixelTales\\frontend\\src\\services\\soundService.ts", "source_location": "L230", "weight": 1.0}, {"source": "services_soundservice_soundservice", "target": "services_soundservice_soundservice_setenabled", "relation": "method", "confidence": "EXTRACTED", "source_file": "D:\\Development\\PixelTales(Image bug fixed)\\PixelTales\\frontend\\src\\services\\soundService.ts", "source_location": "L240", "weight": 1.0}, {"source": "services_soundservice_soundservice", "target": "services_soundservice_soundservice_isenabled", "relation": "method", "confidence": "EXTRACTED", "source_file": "D:\\Development\\PixelTales(Image bug fixed)\\PixelTales\\frontend\\src\\services\\soundService.ts", "source_location": "L252", "weight": 1.0}, {"source": "services_soundservice_soundservice", "target": "services_soundservice_soundservice_setglobalvolume", "relation": "method", "confidence": "EXTRACTED", "source_file": "D:\\Development\\PixelTales(Image bug fixed)\\PixelTales\\frontend\\src\\services\\soundService.ts", "source_location": "L259", "weight": 1.0}, {"source": "services_soundservice_soundservice", "target": "services_soundservice_soundservice_getglobalvolume", "relation": "method", "confidence": "EXTRACTED", "source_file": "D:\\Development\\PixelTales(Image bug fixed)\\PixelTales\\frontend\\src\\services\\soundService.ts", "source_location": "L273", "weight": 1.0}, {"source": "services_soundservice_soundservice", "target": "services_soundservice_soundservice_preload", "relation": "method", "confidence": "EXTRACTED", "source_file": "D:\\Development\\PixelTales(Image bug fixed)\\PixelTales\\frontend\\src\\services\\soundService.ts", "source_location": "L280", "weight": 1.0}, {"source": "services_soundservice_soundservice", "target": "services_soundservice_soundservice_preloadsounds", "relation": "method", "confidence": "EXTRACTED", "source_file": "D:\\Development\\PixelTales(Image bug fixed)\\PixelTales\\frontend\\src\\services\\soundService.ts", "source_location": "L289", "weight": 1.0}, {"source": "services_soundservice_soundservice", "target": "services_soundservice_soundservice_playsuccesswithhaptic", "relation": "method", "confidence": "EXTRACTED", "source_file": "D:\\Development\\PixelTales(Image bug fixed)\\PixelTales\\frontend\\src\\services\\soundService.ts", "source_location": "L296", "weight": 1.0}, {"source": "services_soundservice_soundservice", "target": "services_soundservice_soundservice_playerrorwithhaptic", "relation": "method", "confidence": "EXTRACTED", "source_file": "D:\\Development\\PixelTales(Image bug fixed)\\PixelTales\\frontend\\src\\services\\soundService.ts", "source_location": "L304", "weight": 1.0}, {"source": "services_soundservice_soundservice", "target": "services_soundservice_soundservice_triggerhaptic", "relation": "method", "confidence": "EXTRACTED", "source_file": "D:\\Development\\PixelTales(Image bug fixed)\\PixelTales\\frontend\\src\\services\\soundService.ts", "source_location": "L312", "weight": 1.0}, {"source": "services_soundservice_soundservice", "target": "services_soundservice_soundservice_playhaptic", "relation": "method", "confidence": "EXTRACTED", "source_file": "D:\\Development\\PixelTales(Image bug fixed)\\PixelTales\\frontend\\src\\services\\soundService.ts", "source_location": "L322", "weight": 1.0}, {"source": "services_soundservice_soundservice", "target": "services_soundservice_soundservice_initbackgroundmusic", "relation": "method", "confidence": "EXTRACTED", "source_file": "D:\\Development\\PixelTales(Image bug fixed)\\PixelTales\\frontend\\src\\services\\soundService.ts", "source_location": "L329", "weight": 1.0}, {"source": "services_soundservice_soundservice", "target": "services_soundservice_soundservice_switchtorandomtrack", "relation": "method", "confidence": "EXTRACTED", "source_file": "D:\\Development\\PixelTales(Image bug fixed)\\PixelTales\\frontend\\src\\services\\soundService.ts", "source_location": "L398", "weight": 1.0}, {"source": "services_soundservice_soundservice", "target": "services_soundservice_soundservice_getrandomtrack", "relation": "method", "confidence": "EXTRACTED", "source_file": "D:\\Development\\PixelTales(Image bug fixed)\\PixelTales\\frontend\\src\\services\\soundService.ts", "source_location": "L429", "weight": 1.0}, {"source": "services_soundservice_soundservice", "target": "services_soundservice_soundservice_gettracktoplay", "relation": "method", "confidence": "EXTRACTED", "source_file": "D:\\Development\\PixelTales(Image bug fixed)\\PixelTales\\frontend\\src\\services\\soundService.ts", "source_location": "L446", "weight": 1.0}, {"source": "services_soundservice_soundservice", "target": "services_soundservice_soundservice_startbackgroundmusic", "relation": "method", "confidence": "EXTRACTED", "source_file": "D:\\Development\\PixelTales(Image bug fixed)\\PixelTales\\frontend\\src\\services\\soundService.ts", "source_location": "L456", "weight": 1.0}, {"source": "services_soundservice_soundservice", "target": "services_soundservice_soundservice_stopbackgroundmusic", "relation": "method", "confidence": "EXTRACTED", "source_file": "D:\\Development\\PixelTales(Image bug fixed)\\PixelTales\\frontend\\src\\services\\soundService.ts", "source_location": "L495", "weight": 1.0}, {"source": "services_soundservice_soundservice", "target": "services_soundservice_soundservice_pausebackgroundmusic", "relation": "method", "confidence": "EXTRACTED", "source_file": "D:\\Development\\PixelTales(Image bug fixed)\\PixelTales\\frontend\\src\\services\\soundService.ts", "source_location": "L509", "weight": 1.0}, {"source": "services_soundservice_soundservice", "target": "services_soundservice_soundservice_resumebackgroundmusic", "relation": "method", "confidence": "EXTRACTED", "source_file": "D:\\Development\\PixelTales(Image bug fixed)\\PixelTales\\frontend\\src\\services\\soundService.ts", "source_location": "L518", "weight": 1.0}, {"source": "services_soundservice_soundservice", "target": "services_soundservice_soundservice_fadeinmusic", "relation": "method", "confidence": "EXTRACTED", "source_file": "D:\\Development\\PixelTales(Image bug fixed)\\PixelTales\\frontend\\src\\services\\soundService.ts", "source_location": "L532", "weight": 1.0}, {"source": "services_soundservice_soundservice", "target": "services_soundservice_soundservice_fadeoutmusic", "relation": "method", "confidence": "EXTRACTED", "source_file": "D:\\Development\\PixelTales(Image bug fixed)\\PixelTales\\frontend\\src\\services\\soundService.ts", "source_location": "L558", "weight": 1.0}, {"source": "services_soundservice_soundservice", "target": "services_soundservice_soundservice_setbackgroundmusicvolume", "relation": "method", "confidence": "EXTRACTED", "source_file": "D:\\Development\\PixelTales(Image bug fixed)\\PixelTales\\frontend\\src\\services\\soundService.ts", "source_location": "L590", "weight": 1.0}, {"source": "services_soundservice_soundservice", "target": "services_soundservice_soundservice_getbackgroundmusicvolume", "relation": "method", "confidence": "EXTRACTED", "source_file": "D:\\Development\\PixelTales(Image bug fixed)\\PixelTales\\frontend\\src\\services\\soundService.ts", "source_location": "L602", "weight": 1.0}, {"source": "services_soundservice_soundservice", "target": "services_soundservice_soundservice_setbackgroundmusicenabled", "relation": "method", "confidence": "EXTRACTED", "source_file": "D:\\Development\\PixelTales(Image bug fixed)\\PixelTales\\frontend\\src\\services\\soundService.ts", "source_location": "L609", "weight": 1.0}, {"source": "services_soundservice_soundservice", "target": "services_soundservice_soundservice_isbackgroundmusicenabled", "relation": "method", "confidence": "EXTRACTED", "source_file": "D:\\Development\\PixelTales(Image bug fixed)\\PixelTales\\frontend\\src\\services\\soundService.ts", "source_location": "L621", "weight": 1.0}, {"source": "services_soundservice_soundservice", "target": "services_soundservice_soundservice_isbackgroundmusicplaying", "relation": "method", "confidence": "EXTRACTED", "source_file": "D:\\Development\\PixelTales(Image bug fixed)\\PixelTales\\frontend\\src\\services\\soundService.ts", "source_location": "L628", "weight": 1.0}, {"source": "services_soundservice_soundservice", "target": "services_soundservice_soundservice_setbackgroundmusictrack", "relation": "method", "confidence": "EXTRACTED", "source_file": "D:\\Development\\PixelTales(Image bug fixed)\\PixelTales\\frontend\\src\\services\\soundService.ts", "source_location": "L635", "weight": 1.0}, {"source": "services_soundservice_soundservice", "target": "services_soundservice_soundservice_getselectedmusictrack", "relation": "method", "confidence": "EXTRACTED", "source_file": "D:\\Development\\PixelTales(Image bug fixed)\\PixelTales\\frontend\\src\\services\\soundService.ts", "source_location": "L651", "weight": 1.0}, {"source": "services_soundservice_soundservice", "target": "services_soundservice_soundservice_getavailabletracks", "relation": "method", "confidence": "EXTRACTED", "source_file": "D:\\Development\\PixelTales(Image bug fixed)\\PixelTales\\frontend\\src\\services\\soundService.ts", "source_location": "L658", "weight": 1.0}, {"source": "services_soundservice_soundservice", "target": "services_soundservice_soundservice_getcurrenttrackname", "relation": "method", "confidence": "EXTRACTED", "source_file": "D:\\Development\\PixelTales(Image bug fixed)\\PixelTales\\frontend\\src\\services\\soundService.ts", "source_location": "L665", "weight": 1.0}, {"source": "services_soundservice_soundservice", "target": "services_soundservice_soundservice_gettrackdisplayname", "relation": "method", "confidence": "EXTRACTED", "source_file": "D:\\Development\\PixelTales(Image bug fixed)\\PixelTales\\frontend\\src\\services\\soundService.ts", "source_location": "L683", "weight": 1.0}, {"source": "d_development_pixeltales_image_bug_fixed_pixeltales_frontend_src_services_soundservice_ts", "target": "services_soundservice_soundservice", "relation": "contains", "confidence": "EXTRACTED", "source_file": "D:\\Development\\PixelTales(Image bug fixed)\\PixelTales\\frontend\\src\\services\\soundService.ts", "source_location": "L699", "weight": 1.0}, {"source": "services_soundservice_soundservice_constructor", "target": "services_soundservice_soundservice_preloadcommonsounds", "relation": "calls", "context": "call", "confidence": "EXTRACTED", "source_file": "D:\\Development\\PixelTales(Image bug fixed)\\PixelTales\\frontend\\src\\services\\soundService.ts", "source_location": "L130", "weight": 1.0}, {"source": "services_soundservice_soundservice_playsound", "target": "services_soundservice_soundservice_loadsound", "relation": "calls", "context": "call", "confidence": "EXTRACTED", "source_file": "D:\\Development\\PixelTales(Image bug fixed)\\PixelTales\\frontend\\src\\services\\soundService.ts", "source_location": "L181", "weight": 1.0}, {"source": "services_soundservice_soundservice_setenabled", "target": "services_soundservice_soundservice_stopallsounds", "relation": "calls", "context": "call", "confidence": "EXTRACTED", "source_file": "D:\\Development\\PixelTales(Image bug fixed)\\PixelTales\\frontend\\src\\services\\soundService.ts", "source_location": "L245", "weight": 1.0}, {"source": "services_soundservice_soundservice_preload", "target": "services_soundservice_soundservice_loadsound", "relation": "calls", "context": "call", "confidence": "EXTRACTED", "source_file": "D:\\Development\\PixelTales(Image bug fixed)\\PixelTales\\frontend\\src\\services\\soundService.ts", "source_location": "L282", "weight": 1.0}, {"source": "services_soundservice_soundservice_playsuccesswithhaptic", "target": "services_soundservice_soundservice_playsound", "relation": "calls", "context": "call", "confidence": "EXTRACTED", "source_file": "D:\\Development\\PixelTales(Image bug fixed)\\PixelTales\\frontend\\src\\services\\soundService.ts", "source_location": "L297", "weight": 1.0}, {"source": "services_soundservice_soundservice_playsuccesswithhaptic", "target": "services_soundservice_soundservice_triggerhaptic", "relation": "calls", "context": "call", "confidence": "EXTRACTED", "source_file": "D:\\Development\\PixelTales(Image bug fixed)\\PixelTales\\frontend\\src\\services\\soundService.ts", "source_location": "L298", "weight": 1.0}, {"source": "services_soundservice_soundservice_playerrorwithhaptic", "target": "services_soundservice_soundservice_playsound", "relation": "calls", "context": "call", "confidence": "EXTRACTED", "source_file": "D:\\Development\\PixelTales(Image bug fixed)\\PixelTales\\frontend\\src\\services\\soundService.ts", "source_location": "L305", "weight": 1.0}, {"source": "services_soundservice_soundservice_playerrorwithhaptic", "target": "services_soundservice_soundservice_triggerhaptic", "relation": "calls", "context": "call", "confidence": "EXTRACTED", "source_file": "D:\\Development\\PixelTales(Image bug fixed)\\PixelTales\\frontend\\src\\services\\soundService.ts", "source_location": "L306", "weight": 1.0}, {"source": "services_soundservice_soundservice_playhaptic", "target": "services_soundservice_soundservice_triggerhaptic", "relation": "calls", "context": "call", "confidence": "EXTRACTED", "source_file": "D:\\Development\\PixelTales(Image bug fixed)\\PixelTales\\frontend\\src\\services\\soundService.ts", "source_location": "L323", "weight": 1.0}, {"source": "services_soundservice_soundservice_switchtorandomtrack", "target": "services_soundservice_soundservice_getrandomtrack", "relation": "calls", "context": "call", "confidence": "EXTRACTED", "source_file": "D:\\Development\\PixelTales(Image bug fixed)\\PixelTales\\frontend\\src\\services\\soundService.ts", "source_location": "L403", "weight": 1.0}, {"source": "services_soundservice_soundservice_switchtorandomtrack", "target": "services_soundservice_soundservice_fadeoutmusic", "relation": "calls", "context": "call", "confidence": "EXTRACTED", "source_file": "D:\\Development\\PixelTales(Image bug fixed)\\PixelTales\\frontend\\src\\services\\soundService.ts", "source_location": "L406", "weight": 1.0}, {"source": "services_soundservice_soundservice_switchtorandomtrack", "target": "services_soundservice_soundservice_initbackgroundmusic", "relation": "calls", "context": "call", "confidence": "EXTRACTED", "source_file": "D:\\Development\\PixelTales(Image bug fixed)\\PixelTales\\frontend\\src\\services\\soundService.ts", "source_location": "L409", "weight": 1.0}, {"source": "services_soundservice_soundservice_switchtorandomtrack", "target": "services_soundservice_soundservice_fadeinmusic", "relation": "calls", "context": "call", "confidence": "EXTRACTED", "source_file": "D:\\Development\\PixelTales(Image bug fixed)\\PixelTales\\frontend\\src\\services\\soundService.ts", "source_location": "L416", "weight": 1.0}, {"source": "services_soundservice_soundservice_switchtorandomtrack", "target": "services_soundservice_soundservice_getcurrenttrackname", "relation": "calls", "context": "call", "confidence": "EXTRACTED", "source_file": "D:\\Development\\PixelTales(Image bug fixed)\\PixelTales\\frontend\\src\\services\\soundService.ts", "source_location": "L418", "weight": 1.0}, {"source": "services_soundservice_soundservice_gettracktoplay", "target": "services_soundservice_soundservice_getrandomtrack", "relation": "calls", "context": "call", "confidence": "EXTRACTED", "source_file": "D:\\Development\\PixelTales(Image bug fixed)\\PixelTales\\frontend\\src\\services\\soundService.ts", "source_location": "L448", "weight": 1.0}, {"source": "services_soundservice_soundservice_startbackgroundmusic", "target": "services_soundservice_soundservice_gettracktoplay", "relation": "calls", "context": "call", "confidence": "EXTRACTED", "source_file": "D:\\Development\\PixelTales(Image bug fixed)\\PixelTales\\frontend\\src\\services\\soundService.ts", "source_location": "L463", "weight": 1.0}, {"source": "services_soundservice_soundservice_startbackgroundmusic", "target": "services_soundservice_soundservice_initbackgroundmusic", "relation": "calls", "context": "call", "confidence": "EXTRACTED", "source_file": "D:\\Development\\PixelTales(Image bug fixed)\\PixelTales\\frontend\\src\\services\\soundService.ts", "source_location": "L467", "weight": 1.0}, {"source": "services_soundservice_soundservice_startbackgroundmusic", "target": "services_soundservice_soundservice_fadeinmusic", "relation": "calls", "context": "call", "confidence": "EXTRACTED", "source_file": "D:\\Development\\PixelTales(Image bug fixed)\\PixelTales\\frontend\\src\\services\\soundService.ts", "source_location": "L485", "weight": 1.0}, {"source": "services_soundservice_soundservice_stopbackgroundmusic", "target": "services_soundservice_soundservice_fadeoutmusic", "relation": "calls", "context": "call", "confidence": "EXTRACTED", "source_file": "D:\\Development\\PixelTales(Image bug fixed)\\PixelTales\\frontend\\src\\services\\soundService.ts", "source_location": "L500", "weight": 1.0}, {"source": "services_soundservice_soundservice_setbackgroundmusicenabled", "target": "services_soundservice_soundservice_stopbackgroundmusic", "relation": "calls", "context": "call", "confidence": "EXTRACTED", "source_file": "D:\\Development\\PixelTales(Image bug fixed)\\PixelTales\\frontend\\src\\services\\soundService.ts", "source_location": "L614", "weight": 1.0}, {"source": "services_soundservice_soundservice_setbackgroundmusictrack", "target": "services_soundservice_soundservice_stopbackgroundmusic", "relation": "calls", "context": "call", "confidence": "EXTRACTED", "source_file": "D:\\Development\\PixelTales(Image bug fixed)\\PixelTales\\frontend\\src\\services\\soundService.ts", "source_location": "L642", "weight": 1.0}], "raw_calls": [{"caller_nid": "services_soundservice_soundservice_constructor", "callee": "getItem", "is_member_call": true, "source_file": "D:\\Development\\PixelTales(Image bug fixed)\\PixelTales\\frontend\\src\\services\\soundService.ts", "source_location": "L107"}, {"caller_nid": "services_soundservice_soundservice_constructor", "callee": "getItem", "is_member_call": true, "source_file": "D:\\Development\\PixelTales(Image bug fixed)\\PixelTales\\frontend\\src\\services\\soundService.ts", "source_location": "L111"}, {"caller_nid": "services_soundservice_soundservice_constructor", "callee": "parseFloat", "is_member_call": false, "source_file": "D:\\Development\\PixelTales(Image bug fixed)\\PixelTales\\frontend\\src\\services\\soundService.ts", "source_location": "L113"}, {"caller_nid": "services_soundservice_soundservice_constructor", "callee": "getItem", "is_member_call": true, "source_file": "D:\\Development\\PixelTales(Image bug fixed)\\PixelTales\\frontend\\src\\services\\soundService.ts", "source_location": "L117"}, {"caller_nid": "services_soundservice_soundservice_constructor", "callee": "getItem", "is_member_call": true, "source_file": "D:\\Development\\PixelTales(Image bug fixed)\\PixelTales\\frontend\\src\\services\\soundService.ts", "source_location": "L120"}, {"caller_nid": "services_soundservice_soundservice_constructor", "callee": "parseFloat", "is_member_call": false, "source_file": "D:\\Development\\PixelTales(Image bug fixed)\\PixelTales\\frontend\\src\\services\\soundService.ts", "source_location": "L122"}, {"caller_nid": "services_soundservice_soundservice_constructor", "callee": "getItem", "is_member_call": true, "source_file": "D:\\Development\\PixelTales(Image bug fixed)\\PixelTales\\frontend\\src\\services\\soundService.ts", "source_location": "L125"}, {"caller_nid": "services_soundservice_soundservice_constructor", "callee": "includes", "is_member_call": true, "source_file": "D:\\Development\\PixelTales(Image bug fixed)\\PixelTales\\frontend\\src\\services\\soundService.ts", "source_location": "L126"}, {"caller_nid": "services_soundservice_soundservice_preloadcommonsounds", "callee": "forEach", "is_member_call": true, "source_file": "D:\\Development\\PixelTales(Image bug fixed)\\PixelTales\\frontend\\src\\services\\soundService.ts", "source_location": "L145"}, {"caller_nid": "services_soundservice_soundservice_loadsound", "callee": "set", "is_member_call": true, "source_file": "D:\\Development\\PixelTales(Image bug fixed)\\PixelTales\\frontend\\src\\services\\soundService.ts", "source_location": "L162"}, {"caller_nid": "services_soundservice_soundservice_loadsound", "callee": "warn", "is_member_call": true, "source_file": "D:\\Development\\PixelTales(Image bug fixed)\\PixelTales\\frontend\\src\\services\\soundService.ts", "source_location": "L165"}, {"caller_nid": "services_soundservice_soundservice_playsound", "callee": "get", "is_member_call": true, "source_file": "D:\\Development\\PixelTales(Image bug fixed)\\PixelTales\\frontend\\src\\services\\soundService.ts", "source_location": "L177"}, {"caller_nid": "services_soundservice_soundservice_playsound", "callee": "cloneNode", "is_member_call": true, "source_file": "D:\\Development\\PixelTales(Image bug fixed)\\PixelTales\\frontend\\src\\services\\soundService.ts", "source_location": "L186"}, {"caller_nid": "services_soundservice_soundservice_playsound", "callee": "play", "is_member_call": true, "source_file": "D:\\Development\\PixelTales(Image bug fixed)\\PixelTales\\frontend\\src\\services\\soundService.ts", "source_location": "L202"}, {"caller_nid": "services_soundservice_soundservice_playsound", "callee": "debug", "is_member_call": true, "source_file": "D:\\Development\\PixelTales(Image bug fixed)\\PixelTales\\frontend\\src\\services\\soundService.ts", "source_location": "L212"}, {"caller_nid": "services_soundservice_soundservice_stopsound", "callee": "get", "is_member_call": true, "source_file": "D:\\Development\\PixelTales(Image bug fixed)\\PixelTales\\frontend\\src\\services\\soundService.ts", "source_location": "L220"}, {"caller_nid": "services_soundservice_soundservice_stopsound", "callee": "pause", "is_member_call": true, "source_file": "D:\\Development\\PixelTales(Image bug fixed)\\PixelTales\\frontend\\src\\services\\soundService.ts", "source_location": "L222"}, {"caller_nid": "services_soundservice_soundservice_stopallsounds", "callee": "forEach", "is_member_call": true, "source_file": "D:\\Development\\PixelTales(Image bug fixed)\\PixelTales\\frontend\\src\\services\\soundService.ts", "source_location": "L231"}, {"caller_nid": "services_soundservice_soundservice_setenabled", "callee": "setItem", "is_member_call": true, "source_file": "D:\\Development\\PixelTales(Image bug fixed)\\PixelTales\\frontend\\src\\services\\soundService.ts", "source_location": "L242"}, {"caller_nid": "services_soundservice_soundservice_setenabled", "callee": "String", "is_member_call": false, "source_file": "D:\\Development\\PixelTales(Image bug fixed)\\PixelTales\\frontend\\src\\services\\soundService.ts", "source_location": "L242"}, {"caller_nid": "services_soundservice_soundservice_setglobalvolume", "callee": "max", "is_member_call": true, "source_file": "D:\\Development\\PixelTales(Image bug fixed)\\PixelTales\\frontend\\src\\services\\soundService.ts", "source_location": "L260"}, {"caller_nid": "services_soundservice_soundservice_setglobalvolume", "callee": "min", "is_member_call": true, "source_file": "D:\\Development\\PixelTales(Image bug fixed)\\PixelTales\\frontend\\src\\services\\soundService.ts", "source_location": "L260"}, {"caller_nid": "services_soundservice_soundservice_setglobalvolume", "callee": "setItem", "is_member_call": true, "source_file": "D:\\Development\\PixelTales(Image bug fixed)\\PixelTales\\frontend\\src\\services\\soundService.ts", "source_location": "L261"}, {"caller_nid": "services_soundservice_soundservice_setglobalvolume", "callee": "String", "is_member_call": false, "source_file": "D:\\Development\\PixelTales(Image bug fixed)\\PixelTales\\frontend\\src\\services\\soundService.ts", "source_location": "L261"}, {"caller_nid": "services_soundservice_soundservice_setglobalvolume", "callee": "forEach", "is_member_call": true, "source_file": "D:\\Development\\PixelTales(Image bug fixed)\\PixelTales\\frontend\\src\\services\\soundService.ts", "source_location": "L264"}, {"caller_nid": "services_soundservice_soundservice_preload", "callee": "has", "is_member_call": true, "source_file": "D:\\Development\\PixelTales(Image bug fixed)\\PixelTales\\frontend\\src\\services\\soundService.ts", "source_location": "L281"}, {"caller_nid": "services_soundservice_soundservice_preloadsounds", "callee": "forEach", "is_member_call": true, "source_file": "D:\\Development\\PixelTales(Image bug fixed)\\PixelTales\\frontend\\src\\services\\soundService.ts", "source_location": "L290"}, {"caller_nid": "services_soundservice_soundservice_triggerhaptic", "callee": "vibrate", "is_member_call": true, "source_file": "D:\\Development\\PixelTales(Image bug fixed)\\PixelTales\\frontend\\src\\services\\soundService.ts", "source_location": "L315"}, {"caller_nid": "services_soundservice_soundservice_initbackgroundmusic", "callee": "pause", "is_member_call": true, "source_file": "D:\\Development\\PixelTales(Image bug fixed)\\PixelTales\\frontend\\src\\services\\soundService.ts", "source_location": "L333"}, {"caller_nid": "services_soundservice_soundservice_initbackgroundmusic", "callee": "removeEventListener", "is_member_call": true, "source_file": "D:\\Development\\PixelTales(Image bug fixed)\\PixelTales\\frontend\\src\\services\\soundService.ts", "source_location": "L334"}, {"caller_nid": "services_soundservice_soundservice_initbackgroundmusic", "callee": "addEventListener", "is_member_call": true, "source_file": "D:\\Development\\PixelTales(Image bug fixed)\\PixelTales\\frontend\\src\\services\\soundService.ts", "source_location": "L356"}, {"caller_nid": "services_soundservice_soundservice_initbackgroundmusic", "callee": "addEventListener", "is_member_call": true, "source_file": "D:\\Development\\PixelTales(Image bug fixed)\\PixelTales\\frontend\\src\\services\\soundService.ts", "source_location": "L360"}, {"caller_nid": "services_soundservice_soundservice_initbackgroundmusic", "callee": "error", "is_member_call": true, "source_file": "D:\\Development\\PixelTales(Image bug fixed)\\PixelTales\\frontend\\src\\services\\soundService.ts", "source_location": "L370"}, {"caller_nid": "services_soundservice_soundservice_switchtorandomtrack", "callee": "play", "is_member_call": true, "source_file": "D:\\Development\\PixelTales(Image bug fixed)\\PixelTales\\frontend\\src\\services\\soundService.ts", "source_location": "L415"}, {"caller_nid": "services_soundservice_soundservice_switchtorandomtrack", "callee": "log", "is_member_call": true, "source_file": "D:\\Development\\PixelTales(Image bug fixed)\\PixelTales\\frontend\\src\\services\\soundService.ts", "source_location": "L418"}, {"caller_nid": "services_soundservice_soundservice_switchtorandomtrack", "callee": "error", "is_member_call": true, "source_file": "D:\\Development\\PixelTales(Image bug fixed)\\PixelTales\\frontend\\src\\services\\soundService.ts", "source_location": "L420"}, {"caller_nid": "services_soundservice_soundservice_getrandomtrack", "callee": "filter", "is_member_call": true, "source_file": "D:\\Development\\PixelTales(Image bug fixed)\\PixelTales\\frontend\\src\\services\\soundService.ts", "source_location": "L432"}, {"caller_nid": "services_soundservice_soundservice_getrandomtrack", "callee": "floor", "is_member_call": true, "source_file": "D:\\Development\\PixelTales(Image bug fixed)\\PixelTales\\frontend\\src\\services\\soundService.ts", "source_location": "L435"}, {"caller_nid": "services_soundservice_soundservice_getrandomtrack", "callee": "random", "is_member_call": true, "source_file": "D:\\Development\\PixelTales(Image bug fixed)\\PixelTales\\frontend\\src\\services\\soundService.ts", "source_location": "L435"}, {"caller_nid": "services_soundservice_soundservice_getrandomtrack", "callee": "floor", "is_member_call": true, "source_file": "D:\\Development\\PixelTales(Image bug fixed)\\PixelTales\\frontend\\src\\services\\soundService.ts", "source_location": "L439"}, {"caller_nid": "services_soundservice_soundservice_getrandomtrack", "callee": "random", "is_member_call": true, "source_file": "D:\\Development\\PixelTales(Image bug fixed)\\PixelTales\\frontend\\src\\services\\soundService.ts", "source_location": "L439"}, {"caller_nid": "services_soundservice_soundservice_startbackgroundmusic", "callee": "play", "is_member_call": true, "source_file": "D:\\Development\\PixelTales(Image bug fixed)\\PixelTales\\frontend\\src\\services\\soundService.ts", "source_location": "L481"}, {"caller_nid": "services_soundservice_soundservice_stopbackgroundmusic", "callee": "pause", "is_member_call": true, "source_file": "D:\\Development\\PixelTales(Image bug fixed)\\PixelTales\\frontend\\src\\services\\soundService.ts", "source_location": "L501"}, {"caller_nid": "services_soundservice_soundservice_pausebackgroundmusic", "callee": "pause", "is_member_call": true, "source_file": "D:\\Development\\PixelTales(Image bug fixed)\\PixelTales\\frontend\\src\\services\\soundService.ts", "source_location": "L511"}, {"caller_nid": "services_soundservice_soundservice_resumebackgroundmusic", "callee": "catch", "is_member_call": true, "source_file": "D:\\Development\\PixelTales(Image bug fixed)\\PixelTales\\frontend\\src\\services\\soundService.ts", "source_location": "L522"}, {"caller_nid": "services_soundservice_soundservice_resumebackgroundmusic", "callee": "play", "is_member_call": true, "source_file": "D:\\Development\\PixelTales(Image bug fixed)\\PixelTales\\frontend\\src\\services\\soundService.ts", "source_location": "L522"}, {"caller_nid": "services_soundservice_soundservice_fadeinmusic", "callee": "setInterval", "is_member_call": false, "source_file": "D:\\Development\\PixelTales(Image bug fixed)\\PixelTales\\frontend\\src\\services\\soundService.ts", "source_location": "L541"}, {"caller_nid": "services_soundservice_soundservice_setbackgroundmusicvolume", "callee": "max", "is_member_call": true, "source_file": "D:\\Development\\PixelTales(Image bug fixed)\\PixelTales\\frontend\\src\\services\\soundService.ts", "source_location": "L591"}, {"caller_nid": "services_soundservice_soundservice_setbackgroundmusicvolume", "callee": "min", "is_member_call": true, "source_file": "D:\\Development\\PixelTales(Image bug fixed)\\PixelTales\\frontend\\src\\services\\soundService.ts", "source_location": "L591"}, {"caller_nid": "services_soundservice_soundservice_setbackgroundmusicvolume", "callee": "setItem", "is_member_call": true, "source_file": "D:\\Development\\PixelTales(Image bug fixed)\\PixelTales\\frontend\\src\\services\\soundService.ts", "source_location": "L592"}, {"caller_nid": "services_soundservice_soundservice_setbackgroundmusicvolume", "callee": "String", "is_member_call": false, "source_file": "D:\\Development\\PixelTales(Image bug fixed)\\PixelTales\\frontend\\src\\services\\soundService.ts", "source_location": "L592"}, {"caller_nid": "services_soundservice_soundservice_setbackgroundmusicenabled", "callee": "setItem", "is_member_call": true, "source_file": "D:\\Development\\PixelTales(Image bug fixed)\\PixelTales\\frontend\\src\\services\\soundService.ts", "source_location": "L611"}, {"caller_nid": "services_soundservice_soundservice_setbackgroundmusicenabled", "callee": "String", "is_member_call": false, "source_file": "D:\\Development\\PixelTales(Image bug fixed)\\PixelTales\\frontend\\src\\services\\soundService.ts", "source_location": "L611"}, {"caller_nid": "services_soundservice_soundservice_setbackgroundmusictrack", "callee": "setItem", "is_member_call": true, "source_file": "D:\\Development\\PixelTales(Image bug fixed)\\PixelTales\\frontend\\src\\services\\soundService.ts", "source_location": "L638"}, {"caller_nid": "services_soundservice_soundservice_setbackgroundmusictrack", "callee": "then", "is_member_call": true, "source_file": "D:\\Development\\PixelTales(Image bug fixed)\\PixelTales\\frontend\\src\\services\\soundService.ts", "source_location": "L642"}]}