{"nodes": [{"id": "d_development_pixeltales_image_bug_fixed_pixeltales_docu_session_summary_profile_and_xp_md", "label": "SESSION_SUMMARY_PROFILE_AND_XP.md", "file_type": "document", "source_file": "D:\\Development\\PixelTales(Image bug fixed)\\PixelTales\\docu\\SESSION_SUMMARY_PROFILE_AND_XP.md", "source_location": "L1"}, {"id": "docu_session_summary_profile_and_xp_session_summary_profile_page_xp_system_improvements", "label": "Session Summary: Profile Page & XP System Improvements", "file_type": "document", "source_file": "D:\\Development\\PixelTales(Image bug fixed)\\PixelTales\\docu\\SESSION_SUMMARY_PROFILE_AND_XP.md", "source_location": "L1"}, {"id": "docu_session_summary_profile_and_xp_issues_fixed", "label": "\ud83c\udfaf Issues Fixed", "file_type": "document", "source_file": "D:\\Development\\PixelTales(Image bug fixed)\\PixelTales\\docu\\SESSION_SUMMARY_PROFILE_AND_XP.md", "source_location": "L3"}, {"id": "docu_session_summary_profile_and_xp_issue_1_days_active_bug", "label": "Issue 1: Days Active Bug \u2705", "file_type": "document", "source_file": "D:\\Development\\PixelTales(Image bug fixed)\\PixelTales\\docu\\SESSION_SUMMARY_PROFILE_AND_XP.md", "source_location": "L5"}, {"id": "docu_session_summary_profile_and_xp_issue_2_characters_made_collaborations", "label": "Issue 2: Characters Made \u2192 Collaborations \u2705", "file_type": "document", "source_file": "D:\\Development\\PixelTales(Image bug fixed)\\PixelTales\\docu\\SESSION_SUMMARY_PROFILE_AND_XP.md", "source_location": "L10"}, {"id": "docu_session_summary_profile_and_xp_issue_3_xp_decreases_on_content_deletion", "label": "Issue 3: XP Decreases on Content Deletion \u274c\u2192\u2705", "file_type": "document", "source_file": "D:\\Development\\PixelTales(Image bug fixed)\\PixelTales\\docu\\SESSION_SUMMARY_PROFILE_AND_XP.md", "source_location": "L14"}, {"id": "docu_session_summary_profile_and_xp_changes_made", "label": "\ud83d\udd27 Changes Made", "file_type": "document", "source_file": "D:\\Development\\PixelTales(Image bug fixed)\\PixelTales\\docu\\SESSION_SUMMARY_PROFILE_AND_XP.md", "source_location": "L20"}, {"id": "docu_session_summary_profile_and_xp_1_fixed_days_active_calculation", "label": "1. Fixed Days Active Calculation", "file_type": "document", "source_file": "D:\\Development\\PixelTales(Image bug fixed)\\PixelTales\\docu\\SESSION_SUMMARY_PROFILE_AND_XP.md", "source_location": "L22"}, {"id": "docu_session_summary_profile_and_xp_codeblock_1", "label": "code:typescript (daysActive: Math.floor((new Date().getTime() - new Date('202)", "file_type": "document", "source_file": "D:\\Development\\PixelTales(Image bug fixed)\\PixelTales\\docu\\SESSION_SUMMARY_PROFILE_AND_XP.md", "source_location": "L27"}, {"id": "docu_session_summary_profile_and_xp_codeblock_2", "label": "code:typescript (daysActive: user?.created_at)", "file_type": "document", "source_file": "D:\\Development\\PixelTales(Image bug fixed)\\PixelTales\\docu\\SESSION_SUMMARY_PROFILE_AND_XP.md", "source_location": "L32"}, {"id": "docu_session_summary_profile_and_xp_2_replaced_characters_with_collaborations", "label": "2. Replaced Characters with Collaborations", "file_type": "document", "source_file": "D:\\Development\\PixelTales(Image bug fixed)\\PixelTales\\docu\\SESSION_SUMMARY_PROFILE_AND_XP.md", "source_location": "L42"}, {"id": "docu_session_summary_profile_and_xp_codeblock_3", "label": "code:python (# Added collaboration count)", "file_type": "document", "source_file": "D:\\Development\\PixelTales(Image bug fixed)\\PixelTales\\docu\\SESSION_SUMMARY_PROFILE_AND_XP.md", "source_location": "L45"}, {"id": "docu_session_summary_profile_and_xp_3_implemented_persistent_xp_system", "label": "3. Implemented Persistent XP System", "file_type": "document", "source_file": "D:\\Development\\PixelTales(Image bug fixed)\\PixelTales\\docu\\SESSION_SUMMARY_PROFILE_AND_XP.md", "source_location": "L66"}, {"id": "docu_session_summary_profile_and_xp_database_changes", "label": "Database Changes", "file_type": "document", "source_file": "D:\\Development\\PixelTales(Image bug fixed)\\PixelTales\\docu\\SESSION_SUMMARY_PROFILE_AND_XP.md", "source_location": "L68"}, {"id": "docu_session_summary_profile_and_xp_codeblock_4", "label": "code:python (experience_points = models.PositiveIntegerField(default=0)  )", "file_type": "document", "source_file": "D:\\Development\\PixelTales(Image bug fixed)\\PixelTales\\docu\\SESSION_SUMMARY_PROFILE_AND_XP.md", "source_location": "L71"}, {"id": "docu_session_summary_profile_and_xp_codeblock_5", "label": "code:python (profile.add_experience(amount)  # Award XP)", "file_type": "document", "source_file": "D:\\Development\\PixelTales(Image bug fixed)\\PixelTales\\docu\\SESSION_SUMMARY_PROFILE_AND_XP.md", "source_location": "L77"}, {"id": "docu_session_summary_profile_and_xp_xp_service_created", "label": "XP Service Created", "file_type": "document", "source_file": "D:\\Development\\PixelTales(Image bug fixed)\\PixelTales\\docu\\SESSION_SUMMARY_PROFILE_AND_XP.md", "source_location": "L84"}, {"id": "docu_session_summary_profile_and_xp_api_updates", "label": "API Updates", "file_type": "document", "source_file": "D:\\Development\\PixelTales(Image bug fixed)\\PixelTales\\docu\\SESSION_SUMMARY_PROFILE_AND_XP.md", "source_location": "L109"}, {"id": "docu_session_summary_profile_and_xp_frontend_updates", "label": "Frontend Updates", "file_type": "document", "source_file": "D:\\Development\\PixelTales(Image bug fixed)\\PixelTales\\docu\\SESSION_SUMMARY_PROFILE_AND_XP.md", "source_location": "L121"}, {"id": "docu_session_summary_profile_and_xp_codeblock_6", "label": "code:typescript (interface User {)", "file_type": "document", "source_file": "D:\\Development\\PixelTales(Image bug fixed)\\PixelTales\\docu\\SESSION_SUMMARY_PROFILE_AND_XP.md", "source_location": "L124"}, {"id": "docu_session_summary_profile_and_xp_before_vs_after", "label": "\ud83d\udcca Before vs After", "file_type": "document", "source_file": "D:\\Development\\PixelTales(Image bug fixed)\\PixelTales\\docu\\SESSION_SUMMARY_PROFILE_AND_XP.md", "source_location": "L142"}, {"id": "docu_session_summary_profile_and_xp_days_active", "label": "Days Active", "file_type": "document", "source_file": "D:\\Development\\PixelTales(Image bug fixed)\\PixelTales\\docu\\SESSION_SUMMARY_PROFILE_AND_XP.md", "source_location": "L144"}, {"id": "docu_session_summary_profile_and_xp_profile_stats_display", "label": "Profile Stats Display", "file_type": "document", "source_file": "D:\\Development\\PixelTales(Image bug fixed)\\PixelTales\\docu\\SESSION_SUMMARY_PROFILE_AND_XP.md", "source_location": "L151"}, {"id": "docu_session_summary_profile_and_xp_xp_behavior", "label": "XP Behavior", "file_type": "document", "source_file": "D:\\Development\\PixelTales(Image bug fixed)\\PixelTales\\docu\\SESSION_SUMMARY_PROFILE_AND_XP.md", "source_location": "L159"}, {"id": "docu_session_summary_profile_and_xp_files_modified_created", "label": "\ud83d\uddc2\ufe0f Files Modified/Created", "file_type": "document", "source_file": "D:\\Development\\PixelTales(Image bug fixed)\\PixelTales\\docu\\SESSION_SUMMARY_PROFILE_AND_XP.md", "source_location": "L168"}, {"id": "docu_session_summary_profile_and_xp_backend_files", "label": "Backend Files", "file_type": "document", "source_file": "D:\\Development\\PixelTales(Image bug fixed)\\PixelTales\\docu\\SESSION_SUMMARY_PROFILE_AND_XP.md", "source_location": "L170"}, {"id": "docu_session_summary_profile_and_xp_frontend_files", "label": "Frontend Files", "file_type": "document", "source_file": "D:\\Development\\PixelTales(Image bug fixed)\\PixelTales\\docu\\SESSION_SUMMARY_PROFILE_AND_XP.md", "source_location": "L177"}, {"id": "docu_session_summary_profile_and_xp_documentation_files", "label": "Documentation Files", "file_type": "document", "source_file": "D:\\Development\\PixelTales(Image bug fixed)\\PixelTales\\docu\\SESSION_SUMMARY_PROFILE_AND_XP.md", "source_location": "L181"}, {"id": "docu_session_summary_profile_and_xp_how_to_deploy", "label": "\ud83d\ude80 How to Deploy", "file_type": "document", "source_file": "D:\\Development\\PixelTales(Image bug fixed)\\PixelTales\\docu\\SESSION_SUMMARY_PROFILE_AND_XP.md", "source_location": "L189"}, {"id": "docu_session_summary_profile_and_xp_1_run_database_migration", "label": "1. Run Database Migration", "file_type": "document", "source_file": "D:\\Development\\PixelTales(Image bug fixed)\\PixelTales\\docu\\SESSION_SUMMARY_PROFILE_AND_XP.md", "source_location": "L191"}, {"id": "docu_session_summary_profile_and_xp_codeblock_7", "label": "code:bash (cd backend)", "file_type": "document", "source_file": "D:\\Development\\PixelTales(Image bug fixed)\\PixelTales\\docu\\SESSION_SUMMARY_PROFILE_AND_XP.md", "source_location": "L192"}, {"id": "docu_session_summary_profile_and_xp_2_restart_backend_server", "label": "2. Restart Backend Server", "file_type": "document", "source_file": "D:\\Development\\PixelTales(Image bug fixed)\\PixelTales\\docu\\SESSION_SUMMARY_PROFILE_AND_XP.md", "source_location": "L197"}, {"id": "docu_session_summary_profile_and_xp_codeblock_8", "label": "code:bash (python manage.py runserver)", "file_type": "document", "source_file": "D:\\Development\\PixelTales(Image bug fixed)\\PixelTales\\docu\\SESSION_SUMMARY_PROFILE_AND_XP.md", "source_location": "L198"}, {"id": "docu_session_summary_profile_and_xp_3_clear_frontend_cache_if_needed", "label": "3. Clear Frontend Cache (if needed)", "file_type": "document", "source_file": "D:\\Development\\PixelTales(Image bug fixed)\\PixelTales\\docu\\SESSION_SUMMARY_PROFILE_AND_XP.md", "source_location": "L202"}, {"id": "docu_session_summary_profile_and_xp_codeblock_9", "label": "code:bash (cd frontend)", "file_type": "document", "source_file": "D:\\Development\\PixelTales(Image bug fixed)\\PixelTales\\docu\\SESSION_SUMMARY_PROFILE_AND_XP.md", "source_location": "L203"}, {"id": "docu_session_summary_profile_and_xp_4_test_the_changes", "label": "4. Test the Changes", "file_type": "document", "source_file": "D:\\Development\\PixelTales(Image bug fixed)\\PixelTales\\docu\\SESSION_SUMMARY_PROFILE_AND_XP.md", "source_location": "L208"}, {"id": "docu_session_summary_profile_and_xp_impact", "label": "\ud83d\udcc8 Impact", "file_type": "document", "source_file": "D:\\Development\\PixelTales(Image bug fixed)\\PixelTales\\docu\\SESSION_SUMMARY_PROFILE_AND_XP.md", "source_location": "L216"}, {"id": "docu_session_summary_profile_and_xp_user_experience", "label": "User Experience", "file_type": "document", "source_file": "D:\\Development\\PixelTales(Image bug fixed)\\PixelTales\\docu\\SESSION_SUMMARY_PROFILE_AND_XP.md", "source_location": "L218"}, {"id": "docu_session_summary_profile_and_xp_technical_benefits", "label": "Technical Benefits", "file_type": "document", "source_file": "D:\\Development\\PixelTales(Image bug fixed)\\PixelTales\\docu\\SESSION_SUMMARY_PROFILE_AND_XP.md", "source_location": "L224"}, {"id": "docu_session_summary_profile_and_xp_next_steps_optional", "label": "\ud83c\udfaf Next Steps (Optional)", "file_type": "document", "source_file": "D:\\Development\\PixelTales(Image bug fixed)\\PixelTales\\docu\\SESSION_SUMMARY_PROFILE_AND_XP.md", "source_location": "L232"}, {"id": "docu_session_summary_profile_and_xp_potential_enhancements", "label": "Potential Enhancements", "file_type": "document", "source_file": "D:\\Development\\PixelTales(Image bug fixed)\\PixelTales\\docu\\SESSION_SUMMARY_PROFILE_AND_XP.md", "source_location": "L234"}, {"id": "docu_session_summary_profile_and_xp_backfill_existing_users_optional", "label": "Backfill Existing Users (Optional)", "file_type": "document", "source_file": "D:\\Development\\PixelTales(Image bug fixed)\\PixelTales\\docu\\SESSION_SUMMARY_PROFILE_AND_XP.md", "source_location": "L244"}, {"id": "docu_session_summary_profile_and_xp_codeblock_10", "label": "code:python (# Award XP to existing users based on their activity)", "file_type": "document", "source_file": "D:\\Development\\PixelTales(Image bug fixed)\\PixelTales\\docu\\SESSION_SUMMARY_PROFILE_AND_XP.md", "source_location": "L245"}, {"id": "docu_session_summary_profile_and_xp_testing_checklist", "label": "\u2705 Testing Checklist", "file_type": "document", "source_file": "D:\\Development\\PixelTales(Image bug fixed)\\PixelTales\\docu\\SESSION_SUMMARY_PROFILE_AND_XP.md", "source_location": "L262"}, {"id": "docu_session_summary_profile_and_xp_summary", "label": "\ud83c\udf89 Summary", "file_type": "document", "source_file": "D:\\Development\\PixelTales(Image bug fixed)\\PixelTales\\docu\\SESSION_SUMMARY_PROFILE_AND_XP.md", "source_location": "L277"}], "edges": [{"source": "d_development_pixeltales_image_bug_fixed_pixeltales_docu_session_summary_profile_and_xp_md", "target": "docu_session_summary_profile_and_xp_session_summary_profile_page_xp_system_improvements", "relation": "contains", "confidence": "EXTRACTED", "source_file": "D:\\Development\\PixelTales(Image bug fixed)\\PixelTales\\docu\\SESSION_SUMMARY_PROFILE_AND_XP.md", "source_location": "L1", "weight": 1.0}, {"source": "docu_session_summary_profile_and_xp_session_summary_profile_page_xp_system_improvements", "target": "docu_session_summary_profile_and_xp_issues_fixed", "relation": "contains", "confidence": "EXTRACTED", "source_file": "D:\\Development\\PixelTales(Image bug fixed)\\PixelTales\\docu\\SESSION_SUMMARY_PROFILE_AND_XP.md", "source_location": "L3", "weight": 1.0}, {"source": "docu_session_summary_profile_and_xp_issues_fixed", "target": "docu_session_summary_profile_and_xp_issue_1_days_active_bug", "relation": "contains", "confidence": "EXTRACTED", "source_file": "D:\\Development\\PixelTales(Image bug fixed)\\PixelTales\\docu\\SESSION_SUMMARY_PROFILE_AND_XP.md", "source_location": "L5", "weight": 1.0}, {"source": "docu_session_summary_profile_and_xp_issues_fixed", "target": "docu_session_summary_profile_and_xp_issue_2_characters_made_collaborations", "relation": "contains", "confidence": "EXTRACTED", "source_file": "D:\\Development\\PixelTales(Image bug fixed)\\PixelTales\\docu\\SESSION_SUMMARY_PROFILE_AND_XP.md", "source_location": "L10", "weight": 1.0}, {"source": "docu_session_summary_profile_and_xp_issues_fixed", "target": "docu_session_summary_profile_and_xp_issue_3_xp_decreases_on_content_deletion", "relation": "contains", "confidence": "EXTRACTED", "source_file": "D:\\Development\\PixelTales(Image bug fixed)\\PixelTales\\docu\\SESSION_SUMMARY_PROFILE_AND_XP.md", "source_location": "L14", "weight": 1.0}, {"source": "docu_session_summary_profile_and_xp_session_summary_profile_page_xp_system_improvements", "target": "docu_session_summary_profile_and_xp_changes_made", "relation": "contains", "confidence": "EXTRACTED", "source_file": "D:\\Development\\PixelTales(Image bug fixed)\\PixelTales\\docu\\SESSION_SUMMARY_PROFILE_AND_XP.md", "source_location": "L20", "weight": 1.0}, {"source": "docu_session_summary_profile_and_xp_changes_made", "target": "docu_session_summary_profile_and_xp_1_fixed_days_active_calculation", "relation": "contains", "confidence": "EXTRACTED", "source_file": "D:\\Development\\PixelTales(Image bug fixed)\\PixelTales\\docu\\SESSION_SUMMARY_PROFILE_AND_XP.md", "source_location": "L22", "weight": 1.0}, {"source": "docu_session_summary_profile_and_xp_1_fixed_days_active_calculation", "target": "docu_session_summary_profile_and_xp_codeblock_1", "relation": "contains", "confidence": "EXTRACTED", "source_file": "D:\\Development\\PixelTales(Image bug fixed)\\PixelTales\\docu\\SESSION_SUMMARY_PROFILE_AND_XP.md", "source_location": "L27", "weight": 1.0}, {"source": "docu_session_summary_profile_and_xp_1_fixed_days_active_calculation", "target": "docu_session_summary_profile_and_xp_codeblock_2", "relation": "contains", "confidence": "EXTRACTED", "source_file": "D:\\Development\\PixelTales(Image bug fixed)\\PixelTales\\docu\\SESSION_SUMMARY_PROFILE_AND_XP.md", "source_location": "L32", "weight": 1.0}, {"source": "docu_session_summary_profile_and_xp_changes_made", "target": "docu_session_summary_profile_and_xp_2_replaced_characters_with_collaborations", "relation": "contains", "confidence": "EXTRACTED", "source_file": "D:\\Development\\PixelTales(Image bug fixed)\\PixelTales\\docu\\SESSION_SUMMARY_PROFILE_AND_XP.md", "source_location": "L42", "weight": 1.0}, {"source": "docu_session_summary_profile_and_xp_2_replaced_characters_with_collaborations", "target": "docu_session_summary_profile_and_xp_codeblock_3", "relation": "contains", "confidence": "EXTRACTED", "source_file": "D:\\Development\\PixelTales(Image bug fixed)\\PixelTales\\docu\\SESSION_SUMMARY_PROFILE_AND_XP.md", "source_location": "L45", "weight": 1.0}, {"source": "docu_session_summary_profile_and_xp_changes_made", "target": "docu_session_summary_profile_and_xp_3_implemented_persistent_xp_system", "relation": "contains", "confidence": "EXTRACTED", "source_file": "D:\\Development\\PixelTales(Image bug fixed)\\PixelTales\\docu\\SESSION_SUMMARY_PROFILE_AND_XP.md", "source_location": "L66", "weight": 1.0}, {"source": "docu_session_summary_profile_and_xp_3_implemented_persistent_xp_system", "target": "docu_session_summary_profile_and_xp_database_changes", "relation": "contains", "confidence": "EXTRACTED", "source_file": "D:\\Development\\PixelTales(Image bug fixed)\\PixelTales\\docu\\SESSION_SUMMARY_PROFILE_AND_XP.md", "source_location": "L68", "weight": 1.0}, {"source": "docu_session_summary_profile_and_xp_database_changes", "target": "docu_session_summary_profile_and_xp_codeblock_4", "relation": "contains", "confidence": "EXTRACTED", "source_file": "D:\\Development\\PixelTales(Image bug fixed)\\PixelTales\\docu\\SESSION_SUMMARY_PROFILE_AND_XP.md", "source_location": "L71", "weight": 1.0}, {"source": "docu_session_summary_profile_and_xp_database_changes", "target": "docu_session_summary_profile_and_xp_codeblock_5", "relation": "contains", "confidence": "EXTRACTED", "source_file": "D:\\Development\\PixelTales(Image bug fixed)\\PixelTales\\docu\\SESSION_SUMMARY_PROFILE_AND_XP.md", "source_location": "L77", "weight": 1.0}, {"source": "docu_session_summary_profile_and_xp_3_implemented_persistent_xp_system", "target": "docu_session_summary_profile_and_xp_xp_service_created", "relation": "contains", "confidence": "EXTRACTED", "source_file": "D:\\Development\\PixelTales(Image bug fixed)\\PixelTales\\docu\\SESSION_SUMMARY_PROFILE_AND_XP.md", "source_location": "L84", "weight": 1.0}, {"source": "docu_session_summary_profile_and_xp_3_implemented_persistent_xp_system", "target": "docu_session_summary_profile_and_xp_api_updates", "relation": "contains", "confidence": "EXTRACTED", "source_file": "D:\\Development\\PixelTales(Image bug fixed)\\PixelTales\\docu\\SESSION_SUMMARY_PROFILE_AND_XP.md", "source_location": "L109", "weight": 1.0}, {"source": "docu_session_summary_profile_and_xp_3_implemented_persistent_xp_system", "target": "docu_session_summary_profile_and_xp_frontend_updates", "relation": "contains", "confidence": "EXTRACTED", "source_file": "D:\\Development\\PixelTales(Image bug fixed)\\PixelTales\\docu\\SESSION_SUMMARY_PROFILE_AND_XP.md", "source_location": "L121", "weight": 1.0}, {"source": "docu_session_summary_profile_and_xp_frontend_updates", "target": "docu_session_summary_profile_and_xp_codeblock_6", "relation": "contains", "confidence": "EXTRACTED", "source_file": "D:\\Development\\PixelTales(Image bug fixed)\\PixelTales\\docu\\SESSION_SUMMARY_PROFILE_AND_XP.md", "source_location": "L124", "weight": 1.0}, {"source": "docu_session_summary_profile_and_xp_session_summary_profile_page_xp_system_improvements", "target": "docu_session_summary_profile_and_xp_before_vs_after", "relation": "contains", "confidence": "EXTRACTED", "source_file": "D:\\Development\\PixelTales(Image bug fixed)\\PixelTales\\docu\\SESSION_SUMMARY_PROFILE_AND_XP.md", "source_location": "L142", "weight": 1.0}, {"source": "docu_session_summary_profile_and_xp_before_vs_after", "target": "docu_session_summary_profile_and_xp_days_active", "relation": "contains", "confidence": "EXTRACTED", "source_file": "D:\\Development\\PixelTales(Image bug fixed)\\PixelTales\\docu\\SESSION_SUMMARY_PROFILE_AND_XP.md", "source_location": "L144", "weight": 1.0}, {"source": "docu_session_summary_profile_and_xp_before_vs_after", "target": "docu_session_summary_profile_and_xp_profile_stats_display", "relation": "contains", "confidence": "EXTRACTED", "source_file": "D:\\Development\\PixelTales(Image bug fixed)\\PixelTales\\docu\\SESSION_SUMMARY_PROFILE_AND_XP.md", "source_location": "L151", "weight": 1.0}, {"source": "docu_session_summary_profile_and_xp_before_vs_after", "target": "docu_session_summary_profile_and_xp_xp_behavior", "relation": "contains", "confidence": "EXTRACTED", "source_file": "D:\\Development\\PixelTales(Image bug fixed)\\PixelTales\\docu\\SESSION_SUMMARY_PROFILE_AND_XP.md", "source_location": "L159", "weight": 1.0}, {"source": "docu_session_summary_profile_and_xp_session_summary_profile_page_xp_system_improvements", "target": "docu_session_summary_profile_and_xp_files_modified_created", "relation": "contains", "confidence": "EXTRACTED", "source_file": "D:\\Development\\PixelTales(Image bug fixed)\\PixelTales\\docu\\SESSION_SUMMARY_PROFILE_AND_XP.md", "source_location": "L168", "weight": 1.0}, {"source": "docu_session_summary_profile_and_xp_files_modified_created", "target": "docu_session_summary_profile_and_xp_backend_files", "relation": "contains", "confidence": "EXTRACTED", "source_file": "D:\\Development\\PixelTales(Image bug fixed)\\PixelTales\\docu\\SESSION_SUMMARY_PROFILE_AND_XP.md", "source_location": "L170", "weight": 1.0}, {"source": "docu_session_summary_profile_and_xp_files_modified_created", "target": "docu_session_summary_profile_and_xp_frontend_files", "relation": "contains", "confidence": "EXTRACTED", "source_file": "D:\\Development\\PixelTales(Image bug fixed)\\PixelTales\\docu\\SESSION_SUMMARY_PROFILE_AND_XP.md", "source_location": "L177", "weight": 1.0}, {"source": "docu_session_summary_profile_and_xp_files_modified_created", "target": "docu_session_summary_profile_and_xp_documentation_files", "relation": "contains", "confidence": "EXTRACTED", "source_file": "D:\\Development\\PixelTales(Image bug fixed)\\PixelTales\\docu\\SESSION_SUMMARY_PROFILE_AND_XP.md", "source_location": "L181", "weight": 1.0}, {"source": "docu_session_summary_profile_and_xp_session_summary_profile_page_xp_system_improvements", "target": "docu_session_summary_profile_and_xp_how_to_deploy", "relation": "contains", "confidence": "EXTRACTED", "source_file": "D:\\Development\\PixelTales(Image bug fixed)\\PixelTales\\docu\\SESSION_SUMMARY_PROFILE_AND_XP.md", "source_location": "L189", "weight": 1.0}, {"source": "docu_session_summary_profile_and_xp_how_to_deploy", "target": "docu_session_summary_profile_and_xp_1_run_database_migration", "relation": "contains", "confidence": "EXTRACTED", "source_file": "D:\\Development\\PixelTales(Image bug fixed)\\PixelTales\\docu\\SESSION_SUMMARY_PROFILE_AND_XP.md", "source_location": "L191", "weight": 1.0}, {"source": "docu_session_summary_profile_and_xp_1_run_database_migration", "target": "docu_session_summary_profile_and_xp_codeblock_7", "relation": "contains", "confidence": "EXTRACTED", "source_file": "D:\\Development\\PixelTales(Image bug fixed)\\PixelTales\\docu\\SESSION_SUMMARY_PROFILE_AND_XP.md", "source_location": "L192", "weight": 1.0}, {"source": "docu_session_summary_profile_and_xp_how_to_deploy", "target": "docu_session_summary_profile_and_xp_2_restart_backend_server", "relation": "contains", "confidence": "EXTRACTED", "source_file": "D:\\Development\\PixelTales(Image bug fixed)\\PixelTales\\docu\\SESSION_SUMMARY_PROFILE_AND_XP.md", "source_location": "L197", "weight": 1.0}, {"source": "docu_session_summary_profile_and_xp_2_restart_backend_server", "target": "docu_session_summary_profile_and_xp_codeblock_8", "relation": "contains", "confidence": "EXTRACTED", "source_file": "D:\\Development\\PixelTales(Image bug fixed)\\PixelTales\\docu\\SESSION_SUMMARY_PROFILE_AND_XP.md", "source_location": "L198", "weight": 1.0}, {"source": "docu_session_summary_profile_and_xp_how_to_deploy", "target": "docu_session_summary_profile_and_xp_3_clear_frontend_cache_if_needed", "relation": "contains", "confidence": "EXTRACTED", "source_file": "D:\\Development\\PixelTales(Image bug fixed)\\PixelTales\\docu\\SESSION_SUMMARY_PROFILE_AND_XP.md", "source_location": "L202", "weight": 1.0}, {"source": "docu_session_summary_profile_and_xp_3_clear_frontend_cache_if_needed", "target": "docu_session_summary_profile_and_xp_codeblock_9", "relation": "contains", "confidence": "EXTRACTED", "source_file": "D:\\Development\\PixelTales(Image bug fixed)\\PixelTales\\docu\\SESSION_SUMMARY_PROFILE_AND_XP.md", "source_location": "L203", "weight": 1.0}, {"source": "docu_session_summary_profile_and_xp_how_to_deploy", "target": "docu_session_summary_profile_and_xp_4_test_the_changes", "relation": "contains", "confidence": "EXTRACTED", "source_file": "D:\\Development\\PixelTales(Image bug fixed)\\PixelTales\\docu\\SESSION_SUMMARY_PROFILE_AND_XP.md", "source_location": "L208", "weight": 1.0}, {"source": "docu_session_summary_profile_and_xp_session_summary_profile_page_xp_system_improvements", "target": "docu_session_summary_profile_and_xp_impact", "relation": "contains", "confidence": "EXTRACTED", "source_file": "D:\\Development\\PixelTales(Image bug fixed)\\PixelTales\\docu\\SESSION_SUMMARY_PROFILE_AND_XP.md", "source_location": "L216", "weight": 1.0}, {"source": "docu_session_summary_profile_and_xp_impact", "target": "docu_session_summary_profile_and_xp_user_experience", "relation": "contains", "confidence": "EXTRACTED", "source_file": "D:\\Development\\PixelTales(Image bug fixed)\\PixelTales\\docu\\SESSION_SUMMARY_PROFILE_AND_XP.md", "source_location": "L218", "weight": 1.0}, {"source": "docu_session_summary_profile_and_xp_impact", "target": "docu_session_summary_profile_and_xp_technical_benefits", "relation": "contains", "confidence": "EXTRACTED", "source_file": "D:\\Development\\PixelTales(Image bug fixed)\\PixelTales\\docu\\SESSION_SUMMARY_PROFILE_AND_XP.md", "source_location": "L224", "weight": 1.0}, {"source": "docu_session_summary_profile_and_xp_session_summary_profile_page_xp_system_improvements", "target": "docu_session_summary_profile_and_xp_next_steps_optional", "relation": "contains", "confidence": "EXTRACTED", "source_file": "D:\\Development\\PixelTales(Image bug fixed)\\PixelTales\\docu\\SESSION_SUMMARY_PROFILE_AND_XP.md", "source_location": "L232", "weight": 1.0}, {"source": "docu_session_summary_profile_and_xp_next_steps_optional", "target": "docu_session_summary_profile_and_xp_potential_enhancements", "relation": "contains", "confidence": "EXTRACTED", "source_file": "D:\\Development\\PixelTales(Image bug fixed)\\PixelTales\\docu\\SESSION_SUMMARY_PROFILE_AND_XP.md", "source_location": "L234", "weight": 1.0}, {"source": "docu_session_summary_profile_and_xp_next_steps_optional", "target": "docu_session_summary_profile_and_xp_backfill_existing_users_optional", "relation": "contains", "confidence": "EXTRACTED", "source_file": "D:\\Development\\PixelTales(Image bug fixed)\\PixelTales\\docu\\SESSION_SUMMARY_PROFILE_AND_XP.md", "source_location": "L244", "weight": 1.0}, {"source": "docu_session_summary_profile_and_xp_backfill_existing_users_optional", "target": "docu_session_summary_profile_and_xp_codeblock_10", "relation": "contains", "confidence": "EXTRACTED", "source_file": "D:\\Development\\PixelTales(Image bug fixed)\\PixelTales\\docu\\SESSION_SUMMARY_PROFILE_AND_XP.md", "source_location": "L245", "weight": 1.0}, {"source": "docu_session_summary_profile_and_xp_session_summary_profile_page_xp_system_improvements", "target": "docu_session_summary_profile_and_xp_testing_checklist", "relation": "contains", "confidence": "EXTRACTED", "source_file": "D:\\Development\\PixelTales(Image bug fixed)\\PixelTales\\docu\\SESSION_SUMMARY_PROFILE_AND_XP.md", "source_location": "L262", "weight": 1.0}, {"source": "docu_session_summary_profile_and_xp_session_summary_profile_page_xp_system_improvements", "target": "docu_session_summary_profile_and_xp_summary", "relation": "contains", "confidence": "EXTRACTED", "source_file": "D:\\Development\\PixelTales(Image bug fixed)\\PixelTales\\docu\\SESSION_SUMMARY_PROFILE_AND_XP.md", "source_location": "L277", "weight": 1.0}], "input_tokens": 0, "output_tokens": 0}